Workbook

Sheet Jan-22
D1: 44562
A2: Cliente | B2: Nº Cliente | C2: Nº Instalação | D2: Quant. | E2: % Desconto | F2: Data Fatura | G2: Conta
A3: Lucile Confecções LTDA | B3: 7005713839 | C3: 3003858507 | D3: 777 | E3: 0.1 | G3: 2
A4: CLL Hotel e Turismo | B4: 7008528502 | C4: 3001084033 | D4: 4106 | E4: 0.1 | G4: 1
A5: Academia Planeta Corpo | B5: 7200634170 | C5: 3012153634 | D5: 1780 | E5: 0.1 | F5: Dia 17 | G5: 2
A6: Academia Planeta Corpo | B6: 7005369021 | C6: 3011373971 | D6: 339 | E6: 0.1 | F6: Dia 17 | G6: 2
A7: MD Predial | B7: 7005492088 | C7: 3001449459 | D7: 620 | E7: 0.1 | G7: 2
A8: MD Predial | B8: 7005492088 | C8: 3011504476 | D8: 688 | E8: 0.1 | G8: 2
A9: MD Predial | B9: 7005492088 | C9: 3014340686 | D9: 557 | E9: 0.1 | G9: 2
A10: Fazenda Terra Mirante | B10: 7202158396 | C10: 3002906325 | D10: 195
A11: Irmãs Martins Andrade LTDA-ME | B11: 7005723073 | C11: 3002906806 | D11: 1910 | E11: 0.2 | F11: Dia 17 | G11: 2
A12: Supermercado Bela Vista | B12: 7009098124 | C12: 3003388708 | D12: 3532 | E12: 0.1 | G12: 1
A13: Supermercado Bela Vista | B13: 7009098124 | C13: 3010494037 | D13: 1949 | E13: 0.1 | G13: 1
A14: Supermercado Tia Lia | B14: 7005719624 | C14: 3001268572 | D14: 1181 | E14: 0.1 | G14: 1
A15: A M Lage | B15: 7005623640 | C15: 3002176022 | D15: 5639 | E15: 0.15 | G15: 2
A16: Contabilidade Rocha | B16: 7202048247 | C16: 3003586967 | D16: 86
A17: Contabilidade Rocha | B17: 7201379356 | C17: 3001450164
A18: Contabilidade Rocha | B18: 7202048247 | C18: 3000881551 | D18: 1017
A19: Hotel Itabira | B19: 7005634342 | C19: 3002906805 | D19: 2000 | E19: 0.2 | F19: Dia 17 | G19: 2
A20: Sindicato Metabase Itabira | B20: 7000047224 | C20: 3001450247 | D20: 1944 | E20: 0.1 | G20: 1
A21: Orbis Energia | B21: 7202360028 | C21: 3012107385 | D21: 483
A22: Panificadora Central | B22: 7005728190 | C22: 3002906524 | D22: 8674 | E22: 0.1 | F22: Dia 17 | G22: 1
A23: WB JS Comunicação | B23: 7010498067 | C23: 3013027271 | D23: 1669 | E23: 0.1 | G23: 2
A24: L e R Comercial | B24: 7005590706 | C24: 3006036124 | D24: 98 | E24: 0.1 | G24: 1
A25: L e R Comercial | B25: 7005590706 | C25: 3006066868 | D25: 28 | E25: 0.1 | G25: 1
A26: L e R Comercial | B26: 7005590706 | C26: 3012116454 | D26: 28 | E26: 0.1 | G26: 1
A27: Dominante Comercio de Calçados | B27: 7005707573 | C27: 3004831003 | D27: 45 | E27: 0.1 | G27: 1
A28: Dominante Comercio de Calçados | B28: 7005707573 | C28: 3004831005 | E28: 0.1 | G28: 1
A29: Dominante Comercio de Calçados | B29: 7005707573 | C29: 3006425617 | D29: 634 | E29: 0.1 | G29: 1
A30: ART Pão de Itabira | B30: 7005530163 | C30: 3003562994 | D30: 3007 | E30: 0.2 | G30: 2
A31: Hortifruti QueBom | B31: 7202402563 | C31: 3006700739 | D31: 4080 | E31: 0.15 | G31: 1
A32: Maria do Carmo Oliveira Olimpio | B32: 7202760807 | C32: 3012940288 | D32: 1982 | E32: 0.15 | G32: 2
A33: Jordana de Castro Comercio | B33: 7202482231 | C33: 3004607095 | D33: 295 | E33: 0.1 | G33: 2
A34: Jordana de Castro Comercio | B34: 7202482231 | C34: 3005534144 | D34: 139 | E34: 0.1 | G34: 2
C35: TOTAL | D35: =SUM(D3:D34) -> 49482

Sheet Fev-22
D1: 44593
A2: Cliente | B2: Nº Cliente | C2: Nº Instalação | D2: Quant. | E2: % Desconto | F2: Data Fatura | G2: Conta
A3: Lucile Confecções LTDA | B3: 7005713839 | C3: 3003858507 | D3: 1330 | E3: 0.1 | G3: 2
A4: CLL Hotel e Turismo | B4: 7008528502 | C4: 3001084033 | D4: 5354 | E4: 0.1 | G4: 1
A5: Academia Planeta Corpo | B5: 7200634170 | C5: 3012153634 | D5: 1892 | E5: 0.1 | F5: Dia 17 | G5: 2
A6: Academia Planeta Corpo | B6: 7005369021 | C6: 3011373971 | D6: 183 | E6: 0.1 | F6: Dia 17 | G6: 2
A7: MD Predial | B7: 7005492088 | C7: 3001449459 | D7: 620 | E7: 0.1 | G7: 2
A8: MD Predial | B8: 7005492088 | C8: 3011504476 | D8: 818 | E8: 0.1 | G8: 2
A9: MD Predial | B9: 7005492088 | C9: 3014340686 | D9: 733 | E9: 0.1 | G9: 2
A10: Fazenda Terra Mirante | B10: 7202158396 | C10: 3002906325 | D10: 257
A11: Irmãs Martins Andrade LTDA-ME | B11: 7005723073 | C11: 3002906806 | D11: 2143 | E11: 0.2 | F11: Dia 17 | G11: 2
A12: Supermercado Bela Vista | B12: 7009098124 | C12: 3003388708 | D12: 4803 | E12: 0.1 | G12: 1
A13: Supermercado Bela Vista | B13: 7009098124 | C13: 3010494037 | D13: 2566 | E13: 0.1 | G13: 1
A14: Supermercado Tia Lia | B14: 7005719624 | C14: 3001268572 | D14: 1525 | E14: 0.1 | G14: 1
A15: A M Lage | B15: 7005623640 | C15: 3002176022 | D15: 5982 | E15: 0.15 | G15: 2
A16: Contabilidade Rocha | B16: 7202048247 | C16: 3003586967 | D16: 110
A17: Contabilidade Rocha | B17: 7201379356 | C17: 3001450164
A18: Contabilidade Rocha | B18: 7202048247 | C18: 3000881551 | D18: 1259
A19: Hotel Itabira | B19: 7005634342 | C19: 3002906805 | D19: 2400 | E19: 0.2 | F19: Dia 17 | G19: 2
A20: Sindicato Metabase Itabira | B20: 7000047224 | C20: 3001450247 | D20: 2958 | E20: 0.1 | G20: 1
A21: Orbis Energia | B21: 7202360028 | C21: 3012107385 | D21: 546
A22: Panificadora Central | B22: 7005728190 | C22: 3002906524 | D22: 11298 | E22: 0.1 | F22: Dia 17 | G22: 1
A23: WB JS Comunicação | B23: 7010498067 | C23: 3013027271 | D23: 1983 | E23: 0.1 | G23: 2
A24: L e R Comercial | B24: 7005590706 | C24: 3006036124 | D24: 165 | E24: 0.1 | G24: 1
A25: L e R Comercial | B25: 7005590706 | C25: 3006066868 | D25: 37 | E25: 0.1 | G25: 1
A26: L e R Comercial | B26: 7005590706 | C26: 3012116454 | D26: 37 | E26: 0.1 | G26: 1
A27: Dominante Comercio de Calçados | B27: 7005707573 | C27: 3004831003 | D27: 37 | E27: 0.1 | G27: 1
A28: Dominante Comercio de Calçados | B28: 7005707573 | C28: 3004831005 | D28: 0 | E28: 0.1 | G28: 1
A29: Dominante Comercio de Calçados | B29: 7005707573 | C29: 3006425617 | D29: 0 | E29: 0.1 | G29: 1
A30: ART Pão de Itabira | B30: 7005530163 | C30: 3003562994 | D30: 3533 | E30: 0.2 | G30: 2
A31: Hortifruti QueBom | B31: 7202402563 | C31: 3006700739 | D31: 4407 | E31: 0.15 | G31: 1
A32: Maria do Carmo Oliveira Olimpio | B32: 7202760807 | C32: 3012940288 | D32: 2070 | E32: 0.15 | G32: 2
A33: Jordana de Castro Comercio | B33: 7202482231 | C33: 3004607095 | D33: 367 | E33: 0.1 | G33: 2
A34: Jordana de Castro Comercio | B34: 7202482231 | C34: 3005534144 | D34: 183 | E34: 0.1 | G34: 2
C35: TOTAL | D35: =SUM(D3:D34) -> 59596

Sheet Mar-22
D1: 44621
A2: Cliente | B2: Nº Cliente | C2: Nº Instalação | D2: Quant. | E2: % Desconto | F2: Data Fatura | G2: Conta
A3: Lucile Confecções LTDA | B3: 7005713839 | C3: 3003858507 | D3: 686 | E3: 0.1 | G3: 2
A4: CLL Hotel e Turismo | B4: 7008528502 | C4: 3001084033 | D4: 4330 | E4: 0.1 | G4: 1
A5: Academia Planeta Corpo | B5: 7200634170 | C5: 3012153634 | D5: 642 | E5: 0.1 | F5: Dia 17 | G5: 2
A6: Academia Planeta Corpo | B6: 7005369021 | C6: 3011373971 | D6: 173 | E6: 0.1 | F6: Dia 17 | G6: 2
A7: MD Predial | B7: 7005492088 | C7: 3001449459 | D7: 620 | E7: 0.1 | G7: 2
A8: MD Predial | B8: 7005492088 | C8: 3011504476 | D8: 781 | E8: 0.1 | G8: 2
A9: MD Predial | B9: 7005492088 | C9: 3014340686 | D9: 691 | E9: 0.1 | G9: 2
A10: Fazenda Terra Mirante | B10: 7202158396 | C10: 3002906325 | D10: 242
A11: Irmãs Martins Andrade LTDA-ME | B11: 7005723073 | C11: 3002906806 | D11: 2219 | E11: 0.2 | F11: Dia 17 | G11: 2
A12: Supermercado Bela Vista | B12: 7009098124 | C12: 3003388708 | D12: 3870 | E12: 0.1 | G12: 1
A13: Supermercado Bela Vista | B13: 7009098124 | C13: 3010494037 | D13: 2419 | E13: 0.1 | G13: 1
A14: Supermercado Tia Lia | B14: 7005719624 | C14: 3001268572 | D14: 1453 | E14: 0.1 | G14: 1
A15: A M Lage | B15: 7005623640 | C15: 3002176022 | D15: 6216 | E15: 0.15 | G15: 2
A16: Contabilidade Rocha | B16: 7202048247 | C16: 3003586967 | D16: 104
A17: Contabilidade Rocha | B17: 7201379356 | C17: 3001450164
A18: Contabilidade Rocha | B18: 7202048247 | C18: 3000881551 | D18: 1244
A19: Hotel Itabira | B19: 7005634342 | C19: 3002906805 | D19: 2600 | E19: 0.2 | F19: Dia 17 | G19: 2
A20: Sindicato Metabase Itabira | B20: 7000047224 | C20: 3001450247 | D20: 2070 | E20: 0.1 | G20: 1
A21: Orbis Energia | B21: 7202360028 | C21: 3012107385 | D21: 352
A22: Panificadora Central | B22: 7005728190 | C22: 3002906524 | D22: 6480 | E22: 0.1 | F22: Dia 17 | G22: 1
A23: WB JS Comunicação | B23: 7010498067 | C23: 3013027271 | D23: 1881 | E23: 0.1 | G23: 2
A24: L e R Comercial | B24: 7005590706 | C24: 3006036124 | D24: 38 | E24: 0.1 | G24: 1
A25: L e R Comercial | B25: 7005590706 | C25: 3006066868 | D25: 35 | E25: 0.1 | G25: 1
A26: L e R Comercial | B26: 7005590706 | C26: 3012116454 | D26: 35 | E26: 0.1 | G26: 1
A27: Dominante Comercio de Calçados | B27: 7005707573 | C27: 3004831003 | D27: 35 | E27: 0.1 | G27: 1
A28: Dominante Comercio de Calçados | B28: 7005707573 | C28: 3004831005 | D28: 0 | E28: 0.1 | G28: 1
A29: Dominante Comercio de Calçados | B29: 7005707573 | C29: 3006425617 | D29: 0 | E29: 0.1 | G29: 1
A30: ART Pão de Itabira | B30: 7005530163 | C30: 3003562994 | D30: 4036 | E30: 0.2 | G30: 2
A31: Hortifruti QueBom | B31: 7202402563 | C31: 3006700739 | D31: 4901 | E31: 0.15 | G31: 1
A32: Maria do Carmo Oliveira Olimpio | B32: 7202760807 | C32: 3012940288 | D32: 2464 | E32: 0.15 | G32: 2
A33: Jordana de Castro Comercio | B33: 7202482231 | C33: 3004607095 | D33: 346 | E33: 0.1 | G33: 2
A34: Jordana de Castro Comercio | B34: 7202482231 | C34: 3005534144 | D34: 173 | E34: 0.1 | G34: 2
C35: TOTAL | D35: =SUM(D3:D34) -> 51136

Sheet Abril-22
D1: 44652
A2: Cliente | B2: Nº Cliente | C2: Nº Instalação | D2: Quant. | E2: % Desconto | F2: Data Fatura | G2: Conta
A3: Lucile Confecções LTDA | B3: 7005713839 | C3: 3003858507 | D3: 3653 | E3: 0.1 | G3: 2
A4: CLL Hotel e Turismo | B4: 7008528502 | C4: 3001084033 | D4: 6369 | E4: 0.1 | G4: 1
A5: Academia Planeta Corpo | B5: 7200634170 | C5: 3012153634 | D5: 1930 | E5: 0.1 | F5: Dia 17 | G5: 2
A6: Academia Planeta Corpo | B6: 7005369021 | C6: 3011373971 | D6: 560 | E6: 0.1 | F6: Dia 17 | G6: 2
A7: MD Predial | B7: 7005492088 | C7: 3001449459 | D7: 800 | E7: 0.1 | G7: 2
A8: MD Predial | B8: 7005492088 | C8: 3011504476 | D8: 2700 | E8: 0.1 | G8: 2
A9: MD Predial | B9: 7005492088 | C9: 3014340686 | D9: 1995 | E9: 0.1 | G9: 2
A10: Fazenda Terra Mirante | B10: 7202158396 | C10: 3002906325 | D10: 374
A11: Irmãs Martins Andrade LTDA-ME | B11: 7005723073 | C11: 3002906806 | D11: 1944 | E11: 0.2 | F11: Dia 17 | G11: 2
A12: Supermercado Bela Vista | B12: 7009098124 | C12: 3003388708 | D12: 5180 | E12: 0.1 | G12: 1
A13: Supermercado Bela Vista | B13: 7009098124 | C13: 3010494037 | D13: 10795 | E13: 0.1 | G13: 1
A14: Supermercado Tia Lia | B14: 7005719624 | C14: 3001268572 | D14: 2990 | E14: 0.1 | G14: 1
A15: A M Lage | B15: 7005623640 | C15: 3002176022 | D15: 6384 | E15: 0.15 | G15: 2
A16: Contabilidade Rocha | B16: 7202048247 | C16: 3003586967 | D16: 162
A17: Contabilidade Rocha | B17: 7201379356 | C17: 3001450164
A18: Contabilidade Rocha | B18: 7202048247 | C18: 3000881551 | D18: 1417
A19: Hotel Itabira | B19: 7005634342 | C19: 3002906805 | D19: 2460 | E19: 0.2 | F19: Dia 17 | G19: 2
A20: Sindicato Metabase Itabira | B20: 7000047224 | C20: 3001450247 | D20: 3574 | E20: 0.1 | G20: 1
A21: Orbis Energia | B21: 7202360028 | C21: 3012107385 | D21: 197
A22: Panificadora Central | B22: 7005728190 | C22: 3002906524 | D22: 3494 | E22: 0.1 | F22: Dia 17 | G22: 1
A23: WB JS Comunicação | B23: 7010498067 | C23: 3013027271 | D23: 2480 | E23: 0.1 | G23: 2
A24: L e R Comercial | B24: 7005590706 | C24: 3006036124 | D24: 98 | E24: 0.1 | G24: 1
A25: L e R Comercial | B25: 7005590706 | C25: 3006066868 | E25: 0.1 | G25: 1
A26: L e R Comercial | B26: 7005590706 | C26: 3012116454 | E26: 0.1 | G26: 1
A27: Dominante Comercio de Calçados | B27: 7005707573 | C27: 3004831003 | E27: 0.1 | G27: 1
A28: Dominante Comercio de Calçados | B28: 7005707573 | C28: 3004831005 | E28: 0.1 | G28: 1
A29: Dominante Comercio de Calçados | B29: 7005707573 | C29: 3006425617 | E29: 0.1 | G29: 1
A30: ART Pão de Itabira | B30: 7005530163 | C30: 3003562994 | D30: 4242 | E30: 0.2 | G30: 2
A31: Hortifruti QueBom | B31: 7202402563 | C31: 3006700739 | D31: 4702 | E31: 0.15 | G31: 1
A32: Maria do Carmo Oliveira Olimpio | B32: 7202760807 | C32: 3012940288 | D32: 2501 | E32: 0.15 | G32: 2
A33: Jordana de Castro Comercio | B33: 7202482231 | C33: 3004607095 | D33: 432 | E33: 0.1 | G33: 2
A34: Jordana de Castro Comercio | B34: 7202482231 | C34: 3005534144 | D34: 216 | E34: 0.1 | G34: 2
C35: TOTAL | D35: =SUM(D3:D34) -> 71649

Sheet Maio-22
D1: 44682
A2: Cliente | B2: Nº Cliente | C2: Nº Instalação | D2: Quant. | E2: % Desconto | F2: Data Fatura | G2: Conta
A3: Lucile Confecções LTDA | B3: 7005713839 | C3: 3003858507 | D3: 2478 | E3: 0.1 | G3: 2
A4: CLL Hotel e Turismo | B4: 7008528502 | C4: 3001084033 | D4: 5504 | E4: 0.1 | G4: 1
A5: Academia Planeta Corpo | B5: 7200634170 | C5: 3012153634 | D5: 1523 | E5: 0.1 | G5: 2
A6: Academia Planeta Corpo | B6: 7005369021 | C6: 3011373971 | D6: 635 | E6: 0.1 | G6: 2
A7: MD Predial | B7: 7005492088 | C7: 3001449459 | D7: 700 | E7: 0.1 | G7: 2
A8: MD Predial | B8: 7005492088 | C8: 3011504476 | D8: 1840 | E8: 0.1 | G8: 2
A9: MD Predial | B9: 7005492088 | C9: 3014340686 | D9: 687 | E9: 0.1 | G9: 2
A10: Fazenda Terra Mirante | B10: 7202158396 | C10: 3002906325 | D10: 351
A11: Irmãs Martins Andrade LTDA-ME | B11: 7005723073 | C11: 3002906806 | D11: 2110 | E11: 0.2 | G11: 2
A12: Supermercado Bela Vista | B12: 7009098124 | C12: 3003388708 | D12: 4998 | E12: 0.1 | G12: 1
A13: Supermercado Bela Vista | B13: 7009098124 | C13: 3010494037 | D13: 9531 | E13: 0.1 | G13: 1
A14: Supermercado Tia Lia | B14: 7005719624 | C14: 3001268572 | D14: 2325 | E14: 0.1 | G14: 1
A15: A M Lage | B15: 7005623640 | C15: 3002176022 | D15: 5624 | E15: 0.15 | G15: 2
A16: Contabilidade Rocha | B16: 7202048247 | C16: 3003586967 | D16: 143
A17: Contabilidade Rocha | B17: 7201379356 | C17: 3001450164
A18: Contabilidade Rocha | B18: 7202048247 | C18: 3000881551 | D18: 1294
A19: Hotel Itabira | B19: 7005634342 | C19: 3002906805 | D19: 2540 | E19: 0.2 | G19: 2
A20: Sindicato Metabase Itabira | B20: 7000047224 | C20: 3001450247 | D20: 2361 | E20: 0.1 | G20: 1
A21: Orbis Energia | B21: 7202360028 | C21: 3012107385 | D21: 429
A22: Panificadora Central | B22: 7005728190 | C22: 3002906524 | E22: 0.1 | G22: 1
A23: WB JS Comunicação | B23: 7010498067 | C23: 3013027271 | D23: 2120 | E23: 0.1 | G23: 2
A24: L e R Comercial | B24: 7005590706 | C24: 3006036124 | D24: 67 | E24: 0.1 | G24: 1
A25: L e R Comercial | B25: 7005590706 | C25: 3006066868 | E25: 0.1 | G25: 1
A26: L e R Comercial | B26: 7005590706 | C26: 3012116454 | E26: 0.1 | G26: 1
A27: Dominante Comercio de Calçados | B27: 7005707573 | C27: 3004831003 | E27: 0.1 | G27: 1
A28: Dominante Comercio de Calçados | B28: 7005707573 | C28: 3004831005 | E28: 0.1 | G28: 1
A29: Dominante Comercio de Calçados | B29: 7005707573 | C29: 3006425617 | E29: 0.1 | G29: 1
A30: ART Pão de Itabira | B30: 7005530163 | C30: 3003562994 | D30: 4374 | E30: 0.2 | G30: 2
A31: Hortifruti QueBom | B31: 7202402563 | C31: 3006700739 | D31: 4172 | E31: 0.15 | G31: 1
A32: Maria do Carmo Oliveira Olimpio | B32: 7202760807 | C32: 3012940288 | D32: 1624 | E32: 0.15 | G32: 2
A33: Jordana de Castro Comercio | B33: 7202482231 | C33: 3004607095 | D33: 381 | E33: 0.1 | G33: 2
A34: Jordana de Castro Comercio | B34: 7202482231 | C34: 3005534144 | D34: 191 | E34: 0.1 | G34: 2
C35: TOTAL | D35: =SUM(D3:D34) -> 58002

Sheet Junho-22
D1: 44713
A2: Cliente | B2: Nº Cliente | C2: Nº Instalação | D2: Quant. | E2: % Desconto | F2: Data Fatura | G2: Conta
A3: Lucile Confecções LTDA | B3: 7005713839 | C3: 3003858507 | D3: 817 | E3: 0.1 | G3: 2
A4: CLL Hotel e Turismo | B4: 7008528502 | C4: 3001084033 | D4: 1160 | E4: 0.1 | G4: 1
A5: Academia Planeta Corpo | B5: 7200634170 | C5: 3012153634 | D5: 1160 | E5: 0.1 | G5: 2
A6: Academia Planeta Corpo | B6: 7005369021 | C6: 3011373971 | D6: 740 | E6: 0.1 | G6: 2
A7: MD Predial | B7: 7005492088 | C7: 3001449459 | D7: 620 | E7: 0.1 | G7: 2
A8: MD Predial | B8: 7005492088 | C8: 3011504476 | D8: 1600 | E8: 0.1 | G8: 2
A9: MD Predial | B9: 7005492088 | C9: 3014340686 | D9: 1309 | E9: 0.1 | G9: 2
A10: Fazenda Terra Mirante | B10: 7202158396 | C10: 3002906325 | D10: 413
A11: Irmãs Martins Andrade LTDA-ME | B11: 7005723073 | C11: 3002906806 | D11: 2094 | E11: 0.2 | G11: 2
A12: Supermercado Bela Vista | B12: 7009098124 | C12: 3003388708 | D12: 4687 | E12: 0.1 | G12: 1
A13: Supermercado Bela Vista | B13: 7009098124 | C13: 3010494037 | D13: 10779 | E13: 0.1 | G13: 1
A14: Supermercado Tia Lia | B14: 7005719624 | C14: 3001268572 | D14: 1913 | E14: 0.1 | G14: 1
A15: A M Lage | B15: 7005623640 | C15: 3002176022 | D15: 5896 | E15: 0.15 | G15: 2
A16: Contabilidade Rocha | B16: 7202048247 | C16: 3003586967 | D16: 162
A17: Contabilidade Rocha | B17: 7201379356 | C17: 3001450164
A18: Contabilidade Rocha | B18: 7202048247 | C18: 3000881551 | D18: 1328
A19: Hotel Itabira | B19: 7005634342 | C19: 3002906805 | D19: 2500 | E19: 0.2 | G19: 2
A20: Sindicato Metabase Itabira | B20: 7000047224 | C20: 3001450247 | D20: 1798 | E20: 0.15 | G20: 1
A21: Orbis Energia | B21: 7202360028 | C21: 3012107385 | D21: 357
A22: Panificadora Central | B22: 7005728190 | C22: 3002906524 | E22: 0.1 | G22: 1
A23: WB JS Comunicação | B23: 7010498067 | C23: 3013027271 | D23: 1920 | E23: 0.1 | G23: 2
A24: L e R Comercial | B24: 7005590706 | C24: 3006036124 | E24: 0.1 | G24: 1
A25: L e R Comercial | B25: 7005590706 | C25: 3006066868 | E25: 0.1 | G25: 1
A26: L e R Comercial | B26: 7005590706 | C26: 3012116454 | E26: 0.1 | G26: 1
A27: Dominante Comercio de Calçados | B27: 7005707573 | C27: 3004831003 | E27: 0.1 | G27: 1
A28: Dominante Comercio de Calçados | B28: 7005707573 | C28: 3004831005 | E28: 0.1 | G28: 1
A29: Dominante Comercio de Calçados | B29: 7005707573 | C29: 3006425617 | E29: 0.1 | G29: 1
A30: ART Pão de Itabira | B30: 7005530163 | C30: 3003562994 | D30: 3762 | E30: 0.2 | G30: 2
A31: Hortifruti QueBom | B31: 7202402563 | C31: 3006700739 | D31: 4364 | E31: 0.15 | G31: 1
A32: Maria do Carmo Oliveira Olimpio | B32: 7202760807 | C32: 3012940288 | D32: 1461 | E32: 0.15 | G32: 2
A33: Jordana de Castro Comercio | B33: 7202482231 | C33: 3004607095 | D33: 273 | E33: 0.2 | G33: 2
A34: Jordana de Castro Comercio | B34: 7202482231 | C34: 3005534144 | D34: 196 | E34: 0.2 | G34: 2
A35: Dr Redes (Consórcio) | B35: 7201768092 | C35: 3012189878 | D35: 741
A36: Sanati (Consórcio) | B36: 7201768092 | C36: 3001450194 | D36: 458 | E36: 0.2 | G36: 2
A37: Renato (Orbis) | B37: 7202360028 | C37: 3014183803 | D37: 238
A38: Somatis_Clinica Fisioterapia | B38: 7005466339 | C38: 3013791114 | D38: 0 | E38: 0.2 | G38: 2
A39: Somatis_Clinica Fisioterapia | B39: 7005466339 | C39: 3002619862 | E39: 0.2 | G39: 2
A40: Lanza Magalhães_Dr. Pet | B40: 7200135835 | C40: 3001450251 | E40: 0.15 | G40: 2
A41: Celso Matozinho_Serra 1 (Consórcio) | B41: 7201768092 | C41: 3012262751 | E41: 0.15 | G41: 2 | I41: Somente receberá os créditos no próximo mês
A42: Celso Matozinho_Serra 2 (Consórcio) | B42: 7201768092 | C42: 3007395349 | E42: 0.15 | G42: 2
A43: Celso Matozinho_BH (Consórcio) | B43: 7201768092 | C43: 3001780367 | E43: 0.15 | G43: 2
A44: Celso Matozinho_Itabira (Consórcio) | B44: 7201768092 | C44: 3000914060 | E44: 0.15 | G44: 2
A45: Agatha Rodrigues | B45: 7202806123 | C45: 3003198807 | E45: 0.15 | G45: 2
C46: TOTAL | D46: =SUM(D3:D45) -> 52746

Sheet Julho-22
D1: 44743
A2: Cliente | B2: Nº Cliente | C2: Nº Instalação | D2: Quant. | E2: % Desconto | F2: Data Fatura | G2: Conta
A3: Lucile Confecções LTDA | B3: 7005713839 | C3: 3003858507 | D3: 601 | E3: 0.1 | G3: 2
A4: CLL Hotel e Turismo | B4: 7008528502 | C4: 3001084033 | D4: 5575 | E4: 0.1 | G4: 1
A5: Academia Planeta Corpo | B5: 7200634170 | C5: 3012153634 | D5: 960 | E5: 0.1 | G5: 2
A6: Academia Planeta Corpo | B6: 7005369021 | C6: 3011373971 | D6: 607 | E6: 0.1 | G6: 2
A7: MD Predial | B7: 7005492088 | C7: 3001449459 | D7: 780 | E7: 0.1 | G7: 2
A8: MD Predial | B8: 7005492088 | C8: 3011504476 | D8: 1385 | E8: 0.1 | G8: 2
A9: MD Predial | B9: 7005492088 | C9: 3014340686 | D9: 1729 | E9: 0.1 | G9: 2
A10: Fazenda Terra Mirante | B10: 7202158396 | C10: 3002906325 | D10: 358
A11: Irmãs Martins Andrade LTDA-ME | B11: 7005723073 | C11: 3002906806 | D11: 1972 | E11: 0.2 | G11: 2
A12: Supermercado Bela Vista | B12: 7009098124 | C12: 3003388708 | D12: 4780 | E12: 0.1 | G12: 1
A13: Supermercado Bela Vista | B13: 7009098124 | C13: 3010494037 | D13: 11106 | E13: 0.1 | G13: 1
A14: Supermercado Tia Lia | B14: 7005719624 | C14: 3001268572 | D14: 1359 | E14: 0.1 | G14: 1
A15: A M Lage | B15: 7005623640 | C15: 3002176022 | D15: 5172 | E15: 0.15 | G15: 2
A16: Contabilidade Rocha | B16: 7202048247 | C16: 3003586967 | D16: 167
A17: Contabilidade Rocha | B17: 7202048247 | C17: 3000881551 | D17: 1330
A18: Hotel Itabira | B18: 7005634342 | C18: 3002906805 | D18: 2300 | E18: 0.2 | G18: 2
A19: Sindicato Metabase Itabira | B19: 7000047224 | C19: 3001450247 | D19: 1680 | E19: 0.15 | G19: 1
A20: Orbis Energia | B20: 7202360028 | C20: 3012107385 | D20: 230
A21: WB JS Comunicação | B21: 7010498067 | C21: 3013027271 | D21: 1880 | E21: 0.1 | G21: 2
A22: ART Pão de Itabira | B22: 7005530163 | C22: 3003562994 | D22: 3932 | E22: 0.2 | G22: 2
A23: Hortifruti QueBom | B23: 7202402563 | C23: 3006700739 | D23: 3739 | E23: 0.15 | G23: 1
A24: Maria do Carmo Oliveira Olimpio | B24: 7202760807 | C24: 3012940288 | D24: 1341 | E24: 0.15 | G24: 2
A25: Jordana de Castro Comercio | B25: 7202482231 | C25: 3004607095 | D25: 273 | E25: 0.2 | G25: 2
A26: Jordana de Castro Comercio | B26: 7202482231 | C26: 3005534144 | D26: 197 | E26: 0.2 | G26: 2
A27: Dr Redes (Consórcio) | B27: 7201768092 | C27: 3012189878 | D27: 543
A28: Sanati (Consórcio) | B28: 7201768092 | C28: 3001450194 | D28: 437 | E28: 0.2 | G28: 2
A29: Renato (Orbis) | B29: 7202360028 | C29: 3014183803 | D29: 230
A30: Somatis_Clinica Fisioterapia | B30: 7005466339 | C30: 3013791114 | D30: 184 | E30: 0.2 | G30: 2
A31: Somatis_Clinica Fisioterapia | B31: 7005466339 | C31: 3002619862 | D31: 139 | E31: 0.2 | G31: 2
A32: Lanza Magalhães_Dr. Pet | B32: 7200135835 | C32: 3001450251 | D32: 332 | E32: 0.15 | G32: 2
A33: Celso Matozinho_Serra 1 (Consórcio) | B33: 7201768092 | C33: 3012262751 | D33: 0 | E33: 0.15 | G33: 2
A34: Celso Matozinho_Serra 2 (Consórcio) | B34: 7201768092 | C34: 3007395349 | D34: 0 | E34: 0.15 | G34: 2
A35: Celso Matozinho_BH (Consórcio) | B35: 7201768092 | C35: 3001780367 | D35: 0 | E35: 0.15 | G35: 2
A36: Celso Matozinho_Itabira (Consórcio) | B36: 7201768092 | C36: 3000914060 | D36: 544 | E36: 0.15 | G36: 2
A37: Agatha Rodrigues | B37: 7202806123 | C37: 3003198807 | D37: 1769 | E37: 0.15 | G37: 2
C38: TOTAL | D38: =SUM(D3:D26) -> 53453

Sheet Agosto-22
D1: 44774
A2: Cliente | B2: Nº Cliente | C2: Nº Instalação | D2: Quant. | E2: % Desconto | F2: Data Fatura | G2: Conta | H2: Faturado | I2: Enviado
A3: Lucile Confecções LTDA | B3: 7005713839 | C3: 3003858507 | D3: 638 | E3: 0.1 | F3: 10 | G3: 2 | H3: ok | I3: ok
A4: CLL Hotel e Turismo | B4: 7008528502 | C4: 3001084033 | D4: 5263 | E4: 0.1 | F4: 3 | G4: 1 | H4: ok | I4: ok
A5: Academia Planeta Corpo | B5: 7200634170 | C5: 3012153634 | D5: 1080 | E5: 0.1 | F5: 17 | G5: 2 | H5: ok | I5: ok
A6: Academia Planeta Corpo | B6: 7005369021 | C6: 3011373971 | D6: 438 | E6: 0.1 | F6: 17 | G6: 2 | H6: ok | I6: ok
A7: MD Predial | B7: 7005492088 | C7: 3001449459 | D7: 580 | E7: 0.1 | F7: 6.10 | G7: 2 | H7: ok | I7: ok
A8: MD Predial | B8: 7005492088 | C8: 3011504476 | D8: 1440 | E8: 0.1 | F8: 6.10 | G8: 2 | H8: ok | I8: ok
A9: MD Predial | B9: 7005492088 | C9: 3014340686 | D9: 1449 | E9: 0.1 | F9: 6.10 | G9: 2 | H9: ok | I9: ok
A10: Fazenda Terra Mirante | B10: 7202158396 | C10: 3002906325 | D10: 344 | H10: n/a | I10: n/a
A11: Irmãs Martins Andrade LTDA-ME | B11: 7005723073 | C11: 3002906806 | D11: 1889 | E11: 0.2 | F11: 17 | G11: 2 | H11: ok | I11: n/a
A12: Supermercado Bela Vista | B12: 7009098124 | C12: 3003388708 | D12: 4113 | E12: 0.1 | F12: 2 | G12: 1 | H12: ok | I12: ok
A13: Supermercado Bela Vista | B13: 7009098124 | C13: 3010494037 | D13: 10520 | E13: 0.1 | F13: 26 | G13: 1 | H13: ok | I13: ok
A14: Supermercado Tia Lia | B14: 7005719624 | C14: 3001268572 | D14: 909 | E14: 0.1 | F14: 9 | G14: 1 | H14: ok | I14: ok
A15: A M Lage | B15: 7005623640 | C15: 3002176022 | D15: 4986 | E15: 0.15 | F15: 17 | G15: 2 | H15: ok | I15: n/a
A16: Contabilidade Rocha | B16: 7202048247 | C16: 3003586967 | D16: 164 | H16: n/a | I16: n/a
A17: Contabilidade Rocha | B17: 7202048247 | C17: 3000881551 | D17: 1277 | H17: n/a | I17: n/a
A18: Hotel Itabira | B18: 7005634342 | C18: 3002906805 | D18: 2220 | E18: 0.2 | F18: 17 | G18: 2 | H18: ok | I18: ok
A19: Sindicato Metabase Itabira | B19: 7000047224 | C19: 3001450247 | D19: 1946 | E19: 0.15 | F19: 10 | G19: 1 | H19: ok | I19: ok
A20: Orbis Energia | B20: 7202360028 | C20: 3012107385 | D20: 274 | H20: n/a | I20: n/a
A21: WB JS Comunicação | B21: 7010498067 | C21: 3013027271 | D21: 1600 | E21: 0.1 | F21: 1 | G21: 2 | H21: ok | I21: ok
A22: ART Pão de Itabira | B22: 7005530163 | C22: 3003562994 | D22: 3808 | E22: 0.2 | F22: 3 | G22: 2 | H22: ok | I22: ok
A23: Hortifruti QueBom | B23: 7202402563 | C23: 3006700739 | D23: 4015 | E23: 0.15 | F23: 11 | G23: 1 | H23: ok | I23: ok
A24: Maria do Carmo Oliveira Olimpio | B24: 7202760807 | C24: 3012940288 | D24: 1699 | E24: 0.15 | F24: 17 | G24: 2 | H24: ok | I24: ok
A25: Jordana de Castro Comercio | B25: 7202482231 | C25: 3004607095 | D25: 251 | E25: 0.2 | F25: 6 | G25: 2 | H25: ok | I25: ok
A26: Jordana de Castro Comercio | B26: 7202482231 | C26: 3005534144 | D26: 175 | E26: 0.2 | F26: 6 | G26: 2 | H26: ok | I26: ok
A27: Dr Redes (Consórcio) | B27: 7201768092 | C27: 3012189878 | D27: 603 | H27: n/a | I27: n/a
A28: Sanati (Consórcio) | B28: 7201768092 | C28: 3001450194 | D28: 460 | E28: 0.2 | F28: 11 | G28: 2 | H28: ok
A29: Renato (Orbis) | B29: 7202360028 | C29: 3014183803 | D29: 228 | H29: n/a | I29: n/a
A30: Somatis_Clinica Fisioterapia | B30: 7005466339 | C30: 3013791114 | D30: 143 | E30: 0.2 | F30: 11 | G30: 2 | H30: ok | I30: ok
A31: Somatis_Clinica Fisioterapia | B31: 7005466339 | C31: 3002619862 | D31: 200 | E31: 0.2 | F31: 11 | G31: 2 | H31: ok | I31: ok
A32: Lanza Magalhães_Dr. Pet | B32: 7200135835 | C32: 3001450251 | D32: 378 | E32: 0.15 | F32: 17 | G32: 2 | H32: ok | I32: ok
A33: Celso Matozinho_Serra 1 (Consórcio) | B33: 7201768092 | C33: 3012262751 | D33: 264 | E33: 0.15 | F33: 11 | G33: 2 | H33: ok | I33: ok
A34: Celso Matozinho_Serra 2 (Consórcio) | B34: 7201768092 | C34: 3007395349 | D34: 500 | E34: 0.15 | F34: 11 | G34: 2 | H34: ok | I34: ok
A35: Celso Matozinho_BH (Consórcio) | B35: 7201768092 | C35: 3001780367 | D35: 208 | E35: 0.15 | F35: 11 | G35: 2 | H35: ok | I35: ok
A36: Celso Matozinho_Itabira (Consórcio) | B36: 7201768092 | C36: 3000914060 | D36: 361 | E36: 0.15 | F36: 11 | G36: 2 | H36: ok | I36: ok
A37: Agatha Rodrigues | B37: 7202806123 | C37: 3003198807 | D37: 2195 | E37: 0.15 | F37: 6 | G37: 2 | H37: ok | I37: ok
C38: TOTAL | D38: =SUM(D3:D26) -> 51078
A41: Cervejaria Portal da Canastra Ltda | B41: 7202649326 | C41: 3014018953 | E41: 0.15 | F41: 17 | J41: 3 meses
A42: Faculdade Maximum LTDA | B42: 7010221388 | C42: 3001348433 | E42: 0.2 | J42: 6 meses
A43: Otávio Reis Oliveira Pereira | B43: 7010540003 | C43: 3010642300 | E43: 0.2 | J43: 6 meses
A44: MBLB Acabamentos Ltda | B44: 7005602485 | C44: 3003245697 | E44: 0.2 | J44: 36 meses
A45: Padaria Bouzada III LTDA | B45: 7202646947 | C45: 3004256972 | E45: 0.2 | J45: 5 meses

Sheet Setembro-22
D1: 44805
A2: Cliente | B2: Nº Cliente | C2: Nº Instalação | D2: Quant. | E2: % Desconto | F2: Data Fatura | G2: Conta | H2: Faturado | I2: Enviado
A3: Lucile Confecções LTDA | B3: 7005713839 | C3: 3003858507 | D3: 686 | E3: 0.1 | G3: 2
A4: CLL Hotel e Turismo | B4: 7008528502 | C4: 3001084033 | D4: 5381 | E4: 0.1 | G4: 1
A5: Academia Planeta Corpo | B5: 7200634170 | C5: 3012153634 | D5: 1200 | E5: 0.1 | G5: 2
A6: Academia Planeta Corpo | B6: 7005369021 | C6: 3011373971 | D6: 557.33 | E6: 0.1 | G6: 2
A7: MD Predial | B7: 7005492088 | C7: 3001449459 | D7: 700 | E7: 0.1 | G7: 2
A8: MD Predial | B8: 7005492088 | C8: 3011504476 | D8: 1620 | E8: 0.1 | G8: 2
A9: MD Predial | B9: 7005492088 | C9: 3014340686 | D9: 1784 | E9: 0.1 | G9: 2
A10: Fazenda Terra Mirante | B10: 7202158396 | C10: 3002906325 | D10: 429 | H10: n/a | I10: n/a
A11: Irmãs Martins Andrade LTDA-ME | B11: 7005723073 | C11: 3002906806 | D11: 2321 | E11: 0.2 | G11: 2
A12: Supermercado Bela Vista | B12: 7009098124 | C12: 3003388708 | D12: 4392 | E12: 0.1 | F12: 44827 | G12: 1
A13: Supermercado Bela Vista | B13: 7009098124 | C13: 3010494037 | D13: 10920 | E13: 0.1 | F13: 44827 | G13: 1
A14: Supermercado Tia Lia | B14: 7005719624 | C14: 3001268572 | D14: 1323 | E14: 0.1 | G14: 1
A15: A M Lage | B15: 7005623640 | C15: 3002176022 | D15: 3617 | E15: 0.15 | F15: 17 | G15: 2
A16: Contabilidade Rocha | B16: 7202048247 | C16: 3003586967 | D16: 167 | H16: n/a | I16: n/a
A17: Contabilidade Rocha | B17: 7202048247 | C17: 3000881551 | D17: 1275 | H17: n/a | I17: n/a
A18: Hotel Itabira | B18: 7005634342 | C18: 3002906805 | D18: 2300 | E18: 0.2 | G18: 2
A19: Sindicato Metabase Itabira | B19: 7000047224 | C19: 3001450247 | D19: 2006 | E19: 0.15 | G19: 1
A20: Orbis Energia | B20: 7202360028 | C20: 3012107385 | D20: 315 | H20: n/a | I20: n/a
A21: WB JS Comunicação | B21: 7010498067 | C21: 3013027271 | D21: 2060 | E21: 0.1 | G21: 2
A22: ART Pão de Itabira | B22: 7005530163 | C22: 3003562994 | D22: 4168 | E22: 0.2 | G22: 2
A23: Hortifruti QueBom | B23: 7202402563 | C23: 3006700739 | D23: 3919 | E23: 0.15 | G23: 1
A24: Maria do Carmo Oliveira Olimpio | B24: 7202760807 | C24: 3012940288 | D24: 1828 | E24: 0.15 | G24: 2
A25: Jordana de Castro Comercio | B25: 7202482231 | C25: 3004607095 | D25: 266 | E25: 0.2 | G25: 2
A26: Jordana de Castro Comercio | B26: 7202482231 | C26: 3005534144 | D26: 194 | E26: 0.2 | G26: 2
A27: Dr Redes (Consórcio) | B27: 7201768092 | C27: 3012189878 | D27: 539 | H27: n/a | I27: n/a
A28: Sanati (Consórcio) | B28: 7201768092 | C28: 3001450194 | D28: 512 | E28: 0.2 | G28: 2
A29: Renato (Orbis) | B29: 7202360028 | C29: 3014183803 | D29: 257 | H29: n/a | I29: n/a
A30: Somatis_Clinica Fisioterapia | B30: 7005466339 | C30: 3013791114 | D30: 174 | E30: 0.2 | G30: 2
A31: Somatis_Clinica Fisioterapia | B31: 7005466339 | C31: 3002619862 | D31: 222 | E31: 0.2 | G31: 2
A32: Lanza Magalhães_Dr. Pet | B32: 7200135835 | C32: 3001450251 | D32: 468 | E32: 0.15 | G32: 2
A33: Celso Matozinho_Serra 1 (Consórcio) | B33: 7201768092 | C33: 3012262751 | D33: 610 | E33: 0.15 | G33: 2
A34: Celso Matozinho_Serra 2 (Consórcio) | B34: 7201768092 | C34: 3007395349 | D34: 249 | E34: 0.15 | G34: 2
A35: Celso Matozinho_BH (Consórcio) | B35: 7201768092 | C35: 3001780367 | D35: 236 | E35: 0.15 | G35: 2
A36: Celso Matozinho_Itabira (Consórcio) | B36: 7201768092 | C36: 3000914060 | D36: 355 | E36: 0.15 | G36: 2
A37: Agatha Rodrigues | B37: 7202806123 | C37: 3003198807 | D37: 2638 | E37: 0.15 | G37: 2
C38: TOTAL | D38: =SUM(D3:D26) -> 53428.33
A43: Marcelo Mendes | B43: 7205374759 | C43: 3002175890 | E43: 0.15 | F43: 17 | G43: ? | J43: 3 meses
A44: Carlos Roberto | B44: 7005439127 | C44: 3012512271 | E44: 0.15 | F44: 3 | G44: ? | J44: 3 meses
A45: Simonica Rodrigues | B45: 7200317399 | C45: 3011377412 | E45: 0.2 | F45: 8 | G45: ? | J45: 60 meses
A46: Hortifruti QueBom | B46: 7202402563 | C46: 3012307446 | G46: ?
A47: Cervejaria Portal da Canastra Ltda | B47: 7202649326 | C47: 3014018953 | E47: 0.15 | F47: 17 | G47: ? | J47: 3 meses
A48: Faculdade Maximum LTDA | B48: 7010221388 | C48: 3001348433 | E48: 0.2 | G48: ? | J48: 6 meses
A49: Otávio Reis Oliveira Pereira | B49: 7010540003 | C49: 3010642300 | E49: 0.2 | G49: ? | J49: 6 meses
A50: MBLB Acabamentos Ltda | B50: 7005602485 | C50: 3003245697 | E50: 0.2 | G50: ? | J50: 36 meses
A51: Padaria Bouzada III LTDA | B51: 7202646947 | C51: 3004256972 | E51: 0.2 | G51: ? | J51: 5 meses
A52: Fabrica Gelo Norma | B52: 7200746623 | C52: 3002725236 | E52: 0.2 | F52: 17 | G52: ? | J52: 6 meses
A53: Ortecon Acessoria LTDA | B53: 7010076392 | C53: 3011515927 | E53: 0.15 | F53: 25 | G53: ? | J53: 3 meses
A54: ='Consumo Médio - Clientes'!A46 -> Zilda Soares da Costa Ltda | B54: ='Consumo Médio - Clientes'!B46 -> 0 | C54: ='Consumo Médio - Clientes'!C46 -> 3000886634 | E54: 0.15 | G54: ? | J54: 3 meses

Sheet Outubro-22
D1: 44835 | J1: Custo da Tarifa PASEP | K1: Custo da Tarifa COFINS | L1: Custo da Tarifa c/ ICMS 18% | M1: Custo da Tarifa injetado s/ Pasep / Cofins | N1: Custo de Disponibilidade
A2: Cliente | B2: Nº Cliente | C2: Nº Instalação | D2: Quant. | E2: % Desconto | F2: Data Fatura | G2: Conta | I2: Custo da Tarifa (sem imposto) | J2: 0.0069 | K2: 0.0318
A3: Lucile Confecções LTDA | B3: 7005713839 | C3: 3003858507 | D3: 1116 | E3: 0.1 | G3: 2 | J3: =I3/(1-$K$2-$J$2) -> 0 | M3: =L3-(J3-I3) -> 0
A4: CLL Hotel e Turismo | B4: 7008528502 | C4: 3001084033 | D4: 5274 | E4: 0.1 | G4: 1 | I4: 0.65313 | J4: =I4/(1-$K$2-$J$2) -> 0.6794237 | L4: 0.74377646 | M4: =L4-(J4-I4) -> 0.71748276
A5: Academia Planeta Corpo | B5: 7200634170 | C5: 3012153634 | D5: 1300 | E5: 0.1 | G5: 2 | J5: =I5/(1-$K$2-$J$2) -> 0 | M5: =L5-(J5-I5) -> 0
A6: Academia Planeta Corpo | B6: 7005369021 | C6: 3011373971 | D6: 762 | E6: 0.1 | G6: 2 | I6: 0.65313 | J6: =I6/(1-$K$2-$J$2) -> 0.6794237 | L6: 0.74377646 | M6: =L6-(J6-I6) -> 0.71748276
A7: MD Predial | B7: 7005492088 | C7: 3001449459 | D7: 900 | E7: 0.1 | G7: 2 | J7: =I7/(1-$K$2-$J$2) -> 0 | M7: =L7-(J7-I7) -> 0
A8: MD Predial | B8: 7005492088 | C8: 3011504476 | D8: 1625 | E8: 0.1 | G8: 2 | J8: =I8/(1-$K$2-$J$2) -> 0 | M8: =L8-(J8-I8) -> 0
A9: MD Predial | B9: 7005492088 | C9: 3014340686 | D9: 1459 | E9: 0.1 | G9: 2 | I9: 0.65313 | J9: =I9/(1-$K$2-$J$2) -> 0.6794237 | L9: 0.74377646 | M9: =L9-(J9-I9) -> 0.71748276
A10: Fazenda Terra Mirante | B10: 7202158396 | C10: 3002906325 | D10: 357 | J10: =I10/(1-$K$2-$J$2) -> 0 | M10: =L10-(J10-I10) -> 0
A11: Irmãs Martins Andrade LTDA-ME | B11: 7005723073 | C11: 3002906806 | D11: 2064 | E11: 0.2 | G11: 2 | I11: 0.65313 | J11: =I11/(1-$K$2-$J$2) -> 0.6794237 | L11: 0.74377646 | M11: =L11-(J11-I11) -> 0.71748276
A12: Supermercado Bela Vista | B12: 7009098124 | C12: 3003388708 | D12: 3649 | E12: 0.1 | F12: 44827 | G12: 1 | I12: 0.65313 | J12: =I12/(1-$K$2-$J$2) -> 0.6794237 | L12: 0.74377646 | M12: =L12-(J12-I12) -> 0.71748276
A13: Supermercado Bela Vista | B13: 7009098124 | C13: 3010494037 | D13: 9708 | E13: 0.1 | F13: 44827 | G13: 1 | I13: 0.65313 | J13: =I13/(1-$K$2-$J$2) -> 0.6794237 | L13: 0.74377646 | M13: =L13-(J13-I13) -> 0.71748276
A14: Supermercado Tia Lia | B14: 7005719624 | C14: 3001268572 | D14: 856 | E14: 0.1 | G14: 1 | I14: 0.65313 | J14: =I14/(1-$K$2-$J$2) -> 0.6794237 | L14: 0.74377646 | M14: =L14-(J14-I14) -> 0.71748276
A15: A M Lage | B15: 7005623640 | C15: 3002176022 | D15: 3974 | E15: 0.15 | F15: 17 | G15: 2 | J15: =I15/(1-$K$2-$J$2) -> 0 | M15: =L15-(J15-I15) -> 0
A16: Contabilidade Rocha | B16: 7202048247 | C16: 3003586967 | D16: 189 | J16: =I16/(1-$K$2-$J$2) -> 0 | M16: =L16-(J16-I16) -> 0
A17: Contabilidade Rocha | B17: 7202048247 | C17: 3000881551 | D17: 1184 | J17: =I17/(1-$K$2-$J$2) -> 0 | M17: =L17-(J17-I17) -> 0
A18: Hotel Itabira | B18: 7005634342 | C18: 3002906805 | D18: 2260 | E18: 0.2 | G18: 2 | I18: 0.65313 | J18: =I18/(1-$K$2-$J$2) -> 0.6794237 | L18: 0.74377646 | M18: =L18-(J18-I18) -> 0.71748276
A19: Sindicato Metabase Itabira | B19: 7000047224 | C19: 3001450247 | D19: 2631 | E19: 0.15 | G19: 1 | J19: =I19/(1-$K$2-$J$2) -> 0 | M19: =L19-(J19-I19) -> 0
A20: Orbis Energia | B20: 7202360028 | C20: 3012107385 | D20: 380 | J20: =I20/(1-$K$2-$J$2) -> 0 | M20: =L20-(J20-I20) -> 0
A21: WB JS Comunicação | B21: 7010498067 | C21: 3013027271 | D21: 2020 | E21: 0.1 | G21: 2 | I21: 0.65313 | J21: =I21/(1-$K$2-$J$2) -> 0.6794237 | L21: 0.74377646 | M21: =L21-(J21-I21) -> 0.71748276
A22: ART Pão de Itabira | B22: 7005530163 | C22: 3003562994 | D22: 3698 | E22: 0.2 | G22: 2 | I22: 0.65313 | J22: =I22/(1-$K$2-$J$2) -> 0.6794237 | L22: 0.74377646 | M22: =L22-(J22-I22) -> 0.71748276
A23: Hortifruti QueBom | B23: 7202402563 | C23: 3006700739 | D23: 3928 | E23: 0.15 | G23: 1 | J23: =I23/(1-$K$2-$J$2) -> 0 | M23: =L23-(J23-I23) -> 0
A24: Hortifruti QueBom | B24: 7202402563 | C24: 3012307446 | D24: 2417 | E24: 0.15 | I24: 0.65313 | J24: =I24/(1-$K$2-$J$2) -> 0.6794237 | L24: 0.74377646 | M24: =L24-(J24-I24) -> 0.71748276
A25: Maria do Carmo Oliveira Olimpio | B25: 7202760807 | C25: 3012940288 | D25: 2166 | E25: 0.15 | G25: 2 | J25: =I25/(1-$K$2-$J$2) -> 0 | M25: =L25-(J25-I25) -> 0
A26: Jordana de Castro Comercio | B26: 7202482231 | C26: 3004607095 | D26: 320 | E26: 0.2 | G26: 2 | I26: 0.65313 | J26: =I26/(1-$K$2-$J$2) -> 0.6794237 | L26: 0.7432 | M26: =L26-(J26-I26) -> 0.7169063 | N26: 50 | O26: =(D26-N26)*M26 -> 193.5647 | P26: =O26-(O26*E26) -> 154.85176
A27: Jordana de Castro Comercio | B27: 7202482231 | C27: 3005534144 | D27: 191 | E27: 0.2 | G27: 2 | I27: 0.65313 | J27: =I27/(1-$K$2-$J$2) -> 0.6794237 | L27: 0.7432 | M27: =L27-(J27-I27) -> 0.7169063 | N27: 50 | O27: =(D27-N27)*M27 -> 101.08379 | P27: =O27-(O27*E27) -> 80.867031
A28: Dr Redes (Consórcio) | B28: 7201768092 | C28: 3012189878 | D28: 623 | J28: =I28/(1-$K$2-$J$2) -> 0 | M28: =L28-(J28-I28) -> 0
A29: Sanati (Consórcio) | B29: 7201768092 | C29: 3001450194 | D29: 358 | E29: 0.2 | G29: 2 | I29: 0.65313 | J29: =I29/(1-$K$2-$J$2) -> 0.6794237 | L29: 0.74377646 | M29: =L29-(J29-I29) -> 0.71748276
A30: Renato (Orbis) | B30: 7202360028 | C30: 3014183803 | D30: 188 | J30: =I30/(1-$K$2-$J$2) -> 0 | M30: =L30-(J30-I30) -> 0
A31: Somatis_Clinica Fisioterapia | B31: 7005466339 | C31: 3013791114 | D31: 237 | E31: 0.2 | G31: 2 | J31: =I31/(1-$K$2-$J$2) -> 0 | M31: =L31-(J31-I31) -> 0
A32: Somatis_Clinica Fisioterapia | B32: 7005466339 | C32: 3002619862 | D32: 350 | E32: 0.2 | G32: 2 | J32: =I32/(1-$K$2-$J$2) -> 0 | M32: =L32-(J32-I32) -> 0
A33: Lanza Magalhães_Dr. Pet | B33: 7200135835 | C33: 3001450251 | D33: 517 | E33: 0.15 | G33: 2 | J33: =I33/(1-$K$2-$J$2) -> 0 | M33: =L33-(J33-I33) -> 0
A34: Celso Matozinho_Serra 1 (Consórcio) | B34: 7201768092 | C34: 3012262751 | D34: 323 | E34: 0.15 | G34: 2 | J34: =I34/(1-$K$2-$J$2) -> 0 | M34: =L34-(J34-I34) -> 0
A35: Celso Matozinho_Serra 2 (Consórcio) | B35: 7201768092 | C35: 3007395349 | D35: 227 | E35: 0.15 | G35: 2 | J35: =I35/(1-$K$2-$J$2) -> 0 | M35: =L35-(J35-I35) -> 0
A36: Celso Matozinho_BH (Consórcio) | B36: 7201768092 | C36: 3001780367 | D36: 193 | E36: 0.15 | G36: 2 | J36: =I36/(1-$K$2-$J$2) -> 0 | M36: =L36-(J36-I36) -> 0
A37: Celso Matozinho_Itabira (Consórcio) | B37: 7201768092 | C37: 3000914060 | D37: 375 | E37: 0.15 | G37: 2 | I37: 0.65313 | J37: =I37/(1-$K$2-$J$2) -> 0.6794237 | L37: 0.74377646
A38: Agatha Rodrigues | B38: 7202806123 | C38: 3003198807 | D38: 2266 | E38: 0.15 | G38: 2 | I38: 0.65313 | J38: =I38/(1-$K$2-$J$2) -> 0.6794237 | L38: 0.74706632 | M38: =L38-(J38-I38) -> 0.72077262
A39: Marcelo Mendes | B39: 7205374759 | C39: 3002175890 | D39: 342 | E39: 0.15 | F39: 17 | G39: 2 | I39: 0.65313 | J39: =I39/(1-$K$2-$J$2) -> 0.6794237 | L39: 0.7432 | M39: =L39-(J39-I39) -> 0.7169063 | N39: 30 | O39: =(D39-N39)*M39 -> 223.67477 | P39: =O39-(O39*E39) -> 190.12355
A40: Carlos Roberto | B40: 7005439127 | C40: 3012512271 | D40: 348 | E40: 0.15 | F40: 3 | G40: 2 | I40: 0.65313 | J40: =I40/(1-$K$2-$J$2) -> 0.6794237 | L40: 0.7432 | M40: =L40-(J40-I40) -> 0.7169063 | N40: 50 | O40: =(D40-N40)*M40 -> 213.63808 | P40: =O40-(O40*E40) -> 181.59237
A41: Simonica Rodrigues | B41: 7200317399 | C41: 3011377412 | D41: 1184 | E41: 0.2 | F41: 8 | G41: 2 | J41: =I41/(1-$K$2-$J$2) -> 0 | M41: =L41-(J41-I41) -> 0
A42: Cervejaria Portal da Canastra Ltda | B42: 7202649326 | C42: 3014018953 | D42: 1480 | E42: 0.15 | F42: 17 | G42: 2 | I42: 0.65313 | J42: =I42/(1-$K$2-$J$2) -> 0.6794237 | L42: =74.36/100 -> 0.7436 | M42: =L42-(J42-I42) -> 0.7173063 | N42: 74.36 | O42: =(D42-100)*M42 -> 989.8827 | P42: =O42-(O42*E42) -> 841.40029
A43: Faculdade Maximum LTDA | B43: 7010221388 | C43: 3001348433 | D43: 710 | E43: 0.2 | G43: 2 | I43: 0.65313 | J43: =I43/(1-$K$2-$J$2) -> 0.6794237 | L43: 0.74377646 | M43: =L43-(J43-I43) -> 0.71748276
A44: Otávio Reis Oliveira Pereira | B44: 7010540003 | C44: 3010642300 | D44: 423 | E44: 0.2 | G44: 2 | I44: 0.65313 | J44: =I44/(1-$K$2-$J$2) -> 0.6794237 | L44: 0.7432 | M44: =L44-(J44-I44) -> 0.7169063 | N44: 50 | O44: =(D44-N44)*M44 -> 267.40605 | P44: =O44-(O44*E44) -> 213.92484
A45: MBLB Acabamentos Ltda | B45: 7005602485 | C45: 3003245697 | D45: 1495 | E45: 0.2 | G45: 2 | I45: 0.65313 | J45: =I45/(1-$K$2-$J$2) -> 0.6794237 | L45: =37.16/50 -> 0.7432 | M45: =L45-(J45-I45) -> 0.7169063 | N45: 50 | O45: =(D45-N45)*M45 -> 1035.9296 | P45: =O45-(O45*E45) -> 828.74369
A46: Padaria Bouzada III LTDA | B46: 7202646947 | C46: 3004256972 | D46: 3887 | E46: 0.2 | F46: 44861 | G46: 2 | I46: 0.65313 | J46: =I46/(1-$K$2-$J$2) -> 0.6794237 | L46: 0.74377646 | M46: =L46-(J46-I46) -> 0.71748276
A47: Fabrica Gelo Norma | B47: 7200746623 | C47: 3002725236 | D47: 2049 | E47: 0.2 | F47: 17 | G47: 2 | I47: 0.65313 | J47: =I47/(1-$K$2-$J$2) -> 0.6794237 | L47: 0.74377646 | M47: =L47-(J47-I47) -> 0.71748276
A48: Ortecon Acessoria LTDA | B48: 7010076392 | C48: 3011515927 | D48: 1652 | E48: 0.15 | F48: 25 | G48: 2 | I48: 0.65313 | J48: =I48/(1-$K$2-$J$2) -> 0.6794237 | L48: 0.7432 | M48: =L48-(J48-I48) -> 0.7169063 | N48: 50 | O48: =(D48-N48)*M48 -> 1148.4839 | P48: =O48-(O48*E48) -> 976.21131
A49: Zilda Soares da Costa Ltda | B49: 0 | C49: 3000886634 | D49: 0 | E49: 0.15 | G49: 2 | J49: =I49/(1-$K$2-$J$2) -> 0 | M49: =L49-(J49-I49) -> 0
C50: TOTAL | D50: =SUM(D3:D27) -> 54428

Sheet Novembro-22
D1: 44866
A2: Cliente | B2: Nº Cliente | C2: Nº Instalação | D2: Quant. | E2: % Desconto | F2: Data Fatura | G2: Conta | H2: Faturado | I2: Enviado
A3: Lucile Confecções LTDA | B3: 7005713839 | C3: 3003858507 | E3: 0.1 | G3: 2
A4: CLL Hotel e Turismo | B4: 7008528502 | C4: 3001084033 | E4: 0.1 | G4: 1
A5: Academia Planeta Corpo | B5: 7200634170 | C5: 3012153634 | E5: 0.1 | G5: 2
A6: Academia Planeta Corpo | B6: 7005369021 | C6: 3011373971 | E6: 0.1 | G6: 2
A7: MD Predial | B7: 7005492088 | C7: 3001449459 | E7: 0.1 | G7: 2
A8: MD Predial | B8: 7005492088 | C8: 3011504476 | E8: 0.1 | G8: 2
A9: MD Predial | B9: 7005492088 | C9: 3014340686 | E9: 0.1 | G9: 2
A10: Fazenda Terra Mirante | B10: 7202158396 | C10: 3002906325 | H10: n/a | I10: n/a
A11: Irmãs Martins Andrade LTDA-ME | B11: 7005723073 | C11: 3002906806 | E11: 0.2 | G11: 2
A12: Supermercado Bela Vista | B12: 7009098124 | C12: 3003388708 | E12: 0.1 | F12: 44827 | G12: 1
A13: Supermercado Bela Vista | B13: 7009098124 | C13: 3010494037 | E13: 0.1 | F13: 44827 | G13: 1
A14: Supermercado Tia Lia | B14: 7005719624 | C14: 3001268572 | E14: 0.1 | G14: 1
A15: A M Lage | B15: 7005623640 | C15: 3002176022 | E15: 0.15 | F15: 17 | G15: 2
A16: Contabilidade Rocha | B16: 7202048247 | C16: 3003586967 | H16: n/a | I16: n/a
A17: Contabilidade Rocha | B17: 7202048247 | C17: 3000881551 | H17: n/a | I17: n/a
A18: Hotel Itabira | B18: 7005634342 | C18: 3002906805 | E18: 0.2 | G18: 2
A19: Sindicato Metabase Itabira | B19: 7000047224 | C19: 3001450247 | E19: 0.15 | G19: 1
A20: Orbis Energia | B20: 7202360028 | C20: 3012107385 | H20: n/a | I20: n/a
A21: WB JS Comunicação | B21: 7010498067 | C21: 3013027271 | E21: 0.1 | G21: 2
A22: ART Pão de Itabira | B22: 7005530163 | C22: 3003562994 | E22: 0.2 | G22: 2
A23: Hortifruti QueBom | B23: 7202402563 | C23: 3006700739 | E23: 0.15 | G23: 1
A24: Maria do Carmo Oliveira Olimpio | B24: 7202760807 | C24: 3012940288 | E24: 0.15 | G24: 2
A25: Jordana de Castro Comercio | B25: 7202482231 | C25: 3004607095 | E25: 0.2 | G25: 2
A26: Jordana de Castro Comercio | B26: 7202482231 | C26: 3005534144 | E26: 0.2 | G26: 2
A27: Dr Redes (Consórcio) | B27: 7201768092 | C27: 3012189878 | H27: n/a | I27: n/a
A28: Sanati (Consórcio) | B28: 7201768092 | C28: 3001450194 | E28: 0.2 | G28: 2
A29: Renato (Orbis) | B29: 7202360028 | C29: 3014183803 | H29: n/a | I29: n/a
A30: Somatis_Clinica Fisioterapia | B30: 7005466339 | C30: 3013791114 | E30: 0.2 | G30: 2
A31: Somatis_Clinica Fisioterapia | B31: 7005466339 | C31: 3002619862 | E31: 0.2 | G31: 2
A32: Lanza Magalhães_Dr. Pet | B32: 7200135835 | C32: 3001450251 | E32: 0.15 | G32: 2
A33: Celso Matozinho_Serra 1 (Consórcio) | B33: 7201768092 | C33: 3012262751 | E33: 0.15 | G33: 2
A34: Celso Matozinho_Serra 2 (Consórcio) | B34: 7201768092 | C34: 3007395349 | E34: 0.15 | G34: 2
A35: Celso Matozinho_BH (Consórcio) | B35: 7201768092 | C35: 3001780367 | E35: 0.15 | G35: 2
A36: Celso Matozinho_Itabira (Consórcio) | B36: 7201768092 | C36: 3000914060 | E36: 0.15 | G36: 2
A37: Agatha Rodrigues | B37: 7202806123 | C37: 3003198807 | E37: 0.15 | G37: 2
A38: Marcelo Mendes | B38: 7205374759 | C38: 3002175890 | E38: 0.15 | F38: 17
A39: Carlos Roberto | B39: 7005439127 | C39: 3012512271 | E39: 0.15 | F39: 3
A40: Simonica Rodrigues | B40: 7200317399 | C40: 3011377412 | E40: 0.2 | F40: 8
A41: Hortifruti QueBom | B41: 7202402563 | C41: 3012307446
A42: Cervejaria Portal da Canastra Ltda | B42: 7202649326 | C42: 3014018953 | E42: 0.15 | F42: 17
A43: Faculdade Maximum LTDA | B43: 7010221388 | C43: 3001348433 | E43: 0.2
A44: Otávio Reis Oliveira Pereira | B44: 7010540003 | C44: 3010642300 | E44: 0.2
A45: MBLB Acabamentos Ltda | B45: 7005602485 | C45: 3003245697 | E45: 0.2
A46: Padaria Bouzada III LTDA | B46: 7202646947 | C46: 3004256972 | E46: 0.2
A47: Fabrica Gelo Norma | B47: 7200746623 | C47: 3002725236 | E47: 0.2 | F47: 17
A48: Ortecon Acessoria LTDA | B48: 7010076392 | C48: 3011515927 | E48: 0.15 | F48: 25
A49: Zilda Soares da Costa Ltda | B49: 0 | C49: 3000886634 | E49: 0.15
C50: TOTAL | D50: =SUM(D3:D26) -> 0

Sheet Produção
A1: 2018 | E1: 2019 | I1: 2020
A2: Mês | B2: Produção Estimada | C2: Produção Efetiva | E2: Mês | F2: Produção Estimada | G2: Produção Efetiva | I2: Mês | J2: Produção Estimada | K2: Produção Efetiva
A3: Janeiro | B3: 33585 | E3: Janeiro | F3: 33585 | G3: =ROUND(36160*0.975,2) -> 35256 | I3: Janeiro | J3: 40813 | K3: 38688
A4: Fevereiro | B4: 32700 | E4: Fevereiro | F4: 32700 | G4: =ROUND(34800*0.975,2) -> 33930 | I4: Fevereiro | J4: 39741 | K4: 41020
A5: Março | B5: 34800 | E5: Março | F5: 34800 | G5: =+ROUND(29760*0.975,2) -> 29016 | I5: Março | J5: 39410 | K5: 30800
A6: Abril | B6: 34000 | E6: Abril | F6: 34000 | G6: =+ROUND(32880*0.975,2) -> 32058 | I6: Abril | J6: 36895 | K6: 31120
A7: Maio | B7: 34000 | E7: Maio | F7: 34000 | G7: 29200 | I7: Maio | J7: 36904 | K7: 35920
A8: Junho | B8: 34000 | E8: Junho | F8: 34000 | G8: 31434 | I8: Junho | J8: 35547 | K8: 43200
A9: Julho | B9: 35900 | E9: Julho | F9: 35900 | G9: 34008 | I9: Julho | J9: 38621 | K9: 38640
A10: Agosto | B10: 38000 | E10: Agosto | F10: 38000 | G10: 33360 | I10: Agosto | J10: 43317 | K10: 41280
A11: Setembro | B11: 35400 | E11: Setembro | F11: 35400 | G11: 34242 | I11: Setembro | J11: 38413 | K11: 49120
A12: Outubro | B12: 35200 | E12: Outubro | F12: 35200 | G12: 28470 | I12: Outubro | J12: 39665 | K12: 29000
A13: Novembro | B13: 31000 | E13: Novembro | F13: 31000 | G13: 29874 | I13: Novembro | J13: 34286
A14: Dezembro | B14: 31000 | C14: =ROUND(30560*0.975,2) -> 29796 | E14: Dezembro | F14: 31000 | G14: 34710 | I14: Dezembro | J14: 38384
A15: TOTAL | B15: =SUM(B3:B14) -> 409585 | E15: TOTAL | F15: =SUM(F3:F14) -> 409585 | G15: =SUM(G3:G14) -> 385558 | I15: TOTAL | J15: =SUM(J3:J14) -> 461996 | K15: =SUM(K3:K14) -> 378788

Sheet Simulador
H1: Usina | I1: Alexandre - CGH | J1: Funcesi | K1: Alttos | L1: Albuquerque | M1: Fenix - BL1 | N1: Fenix - BL3 | O1: Fenix - BL7
H2: ='Consumo Médio - Clientes'!BN3 -> 53430 | I2: ='Consumo Médio - Clientes'!AX172 -> 469700 | J2: ='Consumo Médio - Clientes'!AX171 -> 0 | K2: ='Consumo Médio - Clientes'!AX173 -> 12000 | L2: ='Consumo Médio - Clientes'!AX174 -> 12000 | M2: ='Consumo Médio - Clientes'!AX175 -> 1000 | N2: ='Consumo Médio - Clientes'!AX176 -> 1000 | O2: ='Consumo Médio - Clientes'!AX177 -> 1000
H3: UC 3013497957 | I3: UC 3013483817 | J3: UC 3009018668 | K3: UC 3007768063 | L3: UC 3014922778 | M3: UC 3013771324 | N3: UC 3013939291 | O3: UC 3013939295
A4: Cliente | B4: Nº Cliente | C4: Nº Instalação | D4: Consumo Médio | E4: % Atendido | F4: Energia Injetada | G4: Saldo GD | H4: % Saldo | I4: % Saldo | J4: % Saldo | K4: % Saldo | L4: % Saldo | M4: % Saldo | N4: % Saldo | O4: % Saldo
A5: ='Consumo Médio - Clientes'!A2 -> Lucile Confecções LTDA | B5: ='Consumo Médio - Clientes'!B2 -> 7005713839 | C5: ='Consumo Médio - Clientes'!C2 -> 3003858507 | D5: ='Consumo Médio - Clientes'!AX2 -> 3308 | E5: =F5/D5 -> 0.88834643 | F5: =SUM(H5*$H$2,I5*$I$2,J5*$J$2,$K$2*K5,$L$2*L5,M5*$M$2,N5*$N$2,O5*$O$2) -> 2938.65 | G5: ='Consumo Médio - Clientes'!AY2 -> 0 | H5: 0.055 | I5: 0 | J5: 0.05 | K5: 0 | L5: 0 | M5: 0 | N5: 0 | O5: 0
A6: ='Consumo Médio - Clientes'!A3 -> CLL Hotel e Turismo | B6: ='Consumo Médio - Clientes'!B3 -> 7008528502 | C6: ='Consumo Médio - Clientes'!C3 -> 3001084033 | D6: ='Consumo Médio - Clientes'!AX3 -> 7707 | E6: =F6/D6 -> 0.00069326586 | F6: =SUM(H6*$H$2,I6*$I$2,J6*$J$2,$K$2*K6,$L$2*L6,M6*$M$2,N6*$N$2,O6*$O$2) -> 5.343 | G6: ='Consumo Médio - Clientes'!AY3 -> 19766 | H6: 0.0001 | I6: 0 | J6: 0.1 | K6: 0 | L6: 0 | M6: 0 | N6: 0 | O6: 0
A7: ='Consumo Médio - Clientes'!A4 -> Academia Planeta Corpo | B7: ='Consumo Médio - Clientes'!B4 -> 7005369021 | C7: ='Consumo Médio - Clientes'!C4 -> 3011373971 | D7: ='Consumo Médio - Clientes'!AX4 -> 467 | E7: =F7/D7 -> 0.011441113 | F7: =SUM(H7*$H$2,I7*$I$2,J7*$J$2,$K$2*K7,$L$2*L7,M7*$M$2,N7*$N$2,O7*$O$2) -> 5.343 | G7: ='Consumo Médio - Clientes'!AY4 -> 1359 | H7: 0.0001 | I7: 0 | J7: 0 | K7: 0 | L7: 0 | M7: 0 | N7: 0 | O7: 0
A8: ='Consumo Médio - Clientes'!A5 -> MD Predial | B8: ='Consumo Médio - Clientes'!B5 -> 7005492088 | C8: ='Consumo Médio - Clientes'!C5 -> 3001449459 | D8: ='Consumo Médio - Clientes'!AX5 -> 1440 | E8: =F8/D8 -> 1.0545833 | F8: =SUM(H8*$H$2,I8*$I$2,J8*$J$2,$K$2*K8,$L$2*L8,M8*$M$2,N8*$N$2,O8*$O$2) -> 1518.6 | G8: ='Consumo Médio - Clientes'!AY5 -> 0 | H8: 0.02 | I8: 0 | J8: 0.1 | K8: 0 | L8: 0 | M8: 0.15 | N8: 0.15 | O8: 0.15
A9: ='Consumo Médio - Clientes'!A6 -> MD Predial | B9: ='Consumo Médio - Clientes'!B6 -> 7005492088 | C9: ='Consumo Médio - Clientes'!C6 -> 3011504476 | D9: ='Consumo Médio - Clientes'!AX6 -> 1867 | E9: =F9/D9 -> 1.0368238 | F9: =SUM(H9*$H$2,I9*$I$2,J9*$J$2,$K$2*K9,$L$2*L9,M9*$M$2,N9*$N$2,O9*$O$2) -> 1935.75 | G9: ='Consumo Médio - Clientes'!AY6 -> 127 | H9: 0.025 | I9: 0 | J9: 0.1 | K9: 0 | L9: 0 | M9: 0.2 | N9: 0.2 | O9: 0.2
A10: ='Consumo Médio - Clientes'!A7 -> MD Predial | B10: ='Consumo Médio - Clientes'!B7 -> 7005492088 | C10: ='Consumo Médio - Clientes'!C7 -> 3014340686 | D10: ='Consumo Médio - Clientes'!AX7 -> 1447 | E10: =F10/D10 -> 1.1531444 | F10: =SUM(H10*$H$2,I10*$I$2,J10*$J$2,$K$2*K10,$L$2*L10,M10*$M$2,N10*$N$2,O10*$O$2) -> 1668.6 | G10: ='Consumo Médio - Clientes'!AY7 -> 0 | H10: 0.02 | I10: 0 | J10: 0.1 | K10: 0 | L10: 0 | M10: 0.2 | N10: 0.2 | O10: 0.2
A11: ='Consumo Médio - Clientes'!A8 -> Fazenda Terra Mirante | B11: ='Consumo Médio - Clientes'!B8 -> 7202158396 | C11: ='Consumo Médio - Clientes'!C8 -> 3002906325 | D11: ='Consumo Médio - Clientes'!AX8 -> 388 | E11: =F11/D11 -> 0.68853093 | F11: =SUM(H11*$H$2,I11*$I$2,J11*$J$2,$K$2*K11,$L$2*L11,M11*$M$2,N11*$N$2,O11*$O$2) -> 267.15 | G11: ='Consumo Médio - Clientes'!AY8 -> 0 | H11: 0.005 | I11: 0 | J11: 0 | K11: 0 | L11: 0 | M11: 0 | N11: 0 | O11: 0
A12: ='Consumo Médio - Clientes'!A9 -> Irmãs Martins Andrade LTDA-ME | B12: ='Consumo Médio - Clientes'!B9 -> 7005723073 | C12: ='Consumo Médio - Clientes'!C9 -> 3002906806 | D12: ='Consumo Médio - Clientes'!AX9 -> 2262 | E12: =F12/D12 -> 0.6229443 | F12: =SUM(H12*$H$2,I12*$I$2,J12*$J$2,$K$2*K12,$L$2*L12,M12*$M$2,N12*$N$2,O12*$O$2) -> 1409.1 | G12: ='Consumo Médio - Clientes'!AY9 -> 4764 | H12: 0 | I12: 0.003 | J12: 0 | K12: 0 | L12: 0 | M12: 0 | N12: 0 | O12: 0
A13: ='Consumo Médio - Clientes'!A10 -> Supermercado Bela Vista | B13: ='Consumo Médio - Clientes'!B10 -> 7009098124 | C13: ='Consumo Médio - Clientes'!C10 -> 3003388708 | D13: ='Consumo Médio - Clientes'!AX10 -> 5293 | E13: =F13/D13 -> 0.88739845 | F13: =SUM(H13*$H$2,I13*$I$2,J13*$J$2,$K$2*K13,$L$2*L13,M13*$M$2,N13*$N$2,O13*$O$2) -> 4697 | G13: ='Consumo Médio - Clientes'!AY10 -> 2658 | H13: 0 | I13: 0.01 | J13: 0 | K13: 0 | L13: 0 | M13: 0 | N13: 0 | O13: 0
A14: ='Consumo Médio - Clientes'!A11 -> Supermercado Bela Vista | B14: ='Consumo Médio - Clientes'!B11 -> 7009098124 | C14: ='Consumo Médio - Clientes'!C11 -> 3010494037 | D14: ='Consumo Médio - Clientes'!AX11 -> 13467 | E14: =F14/D14 -> 0.87194624 | F14: =SUM(H14*$H$2,I14*$I$2,J14*$J$2,$K$2*K14,$L$2*L14,M14*$M$2,N14*$N$2,O14*$O$2) -> 11742.5 | G14: ='Consumo Médio - Clientes'!AY11 -> 8076 | H14: 0 | I14: 0.025 | J14: 0 | K14: 0 | L14: 0 | M14: 0 | N14: 0 | O14: 0
A15: ='Consumo Médio - Clientes'!A12 -> Supermercado Tia Lia | B15: ='Consumo Médio - Clientes'!B12 -> 7005719624 | C15: ='Consumo Médio - Clientes'!C12 -> 3001268572 | D15: ='Consumo Médio - Clientes'!AX12 -> 3097 | E15: =F15/D15 -> 1.020371 | F15: =SUM(H15*$H$2,I15*$I$2,J15*$J$2,$K$2*K15,$L$2*L15,M15*$M$2,N15*$N$2,O15*$O$2) -> 3160.089 | G15: ='Consumo Médio - Clientes'!AY12 -> 0 | H15: 0.0423 | I15: 0 | J15: 0.1 | K15: 0 | L15: 0 | M15: 0.3 | N15: 0.3 | O15: 0.3
A16: ='Consumo Médio - Clientes'!A13 -> A M Lage | B16: ='Consumo Médio - Clientes'!B13 -> 7005623640 | C16: ='Consumo Médio - Clientes'!C13 -> 3002176022 | D16: ='Consumo Médio - Clientes'!AX13 -> 6475 | E16: =F16/D16 -> 0.72540541 | F16: =SUM(H16*$H$2,I16*$I$2,J16*$J$2,$K$2*K16,$L$2*L16,M16*$M$2,N16*$N$2,O16*$O$2) -> 4697 | G16: ='Consumo Médio - Clientes'!AY13 -> 8587 | H16: 0 | I16: 0.01 | J16: 0 | K16: 0 | L16: 0 | M16: 0 | N16: 0 | O16: 0
... A158: ='Consumo Médio - Clientes'!A155 -> Reis & Moraes Sociedade de Advogados | B158: ='Consumo Médio - Clientes'!B155 -> 7203052221 | C158: ='Consumo Médio - Clientes'!C155 -> 3000975425 | D158: ='Consumo Médio - Clientes'!AX155 -> 272 | E158: =F158/D158 -> 0.98216912 | F158: =SUM(H158*$H$2,I158*$I$2,J158*$J$2,$K$2*K158,$L$2*L158,M158*$M$2,N158*$N$2,O158*$O$2) -> 267.15 | G158: ='Consumo Médio - Clientes'!AY155 -> 0 | H158: 0.005 | I158: 0 | J158: 0 | K158: 0 | L158: 0 | M158: 0 | N158: 0 | O158: 0
A159: ='Consumo Médio - Clientes'!A156 -> Rafael Moraes Pereira | B159: ='Consumo Médio - Clientes'!B156 -> 0 | C159: ='Consumo Médio - Clientes'!C156 -> 3014002885 | D159: ='Consumo Médio - Clientes'!AX156 -> 627 | E159: =F159/D159 -> 0.85215311 | F159: =SUM(H159*$H$2,I159*$I$2,J159*$J$2,$K$2*K159,$L$2*L159,M159*$M$2,N159*$N$2,O159*$O$2) -> 534.3 | H159: 0.01 | I159: 0 | J159: 0 | K159: 0 | L159: 0 | M159: 0 | N159: 0 | O159: 0
A160: ='Consumo Médio - Clientes'!A157 -> Francisco Bernardes Texeira | B160: ='Consumo Médio - Clientes'!B157 -> 7002851665 | C160: ='Consumo Médio - Clientes'!C157 -> 3011864998 | D160: ='Consumo Médio - Clientes'!AX157 -> 110.66667 | E160: =F160/D160 -> 0.96560241 | F160: =SUM(H160*$H$2,I160*$I$2,J160*$J$2,$K$2*K160,$L$2*L160,M160*$M$2,N160*$N$2,O160*$O$2) -> 106.86 | H160: 0.002 | I160: 0 | J160: 0 | K160: 0 | L160: 0 | M160: 0 | N160: 0 | O160: 0
A161: ='Consumo Médio - Clientes'!A158 -> Glaucia Silva Oda | B161: ='Consumo Médio - Clientes'!B158 -> 0 | C161: ='Consumo Médio - Clientes'!C158 -> 3010214309 | D161: ='Consumo Médio - Clientes'!AX158 -> #DIV/0! | E161: =F161/D161 -> #DIV/0! | F161: =SUM(H161*$H$2,I161*$I$2,J161*$J$2,$K$2*K161,$L$2*L161,M161*$M$2,N161*$N$2,O161*$O$2) -> 0 | H161: 0 | I161: 0 | J161: 0 | K161: 0 | L161: 0 | M161: 0 | N161: 0 | O161: 0
A162: ='Consumo Médio - Clientes'!A159 -> Breno Denubila Almeida | B162: ='Consumo Médio - Clientes'!B159 -> 7201802268 | C162: ='Consumo Médio - Clientes'!C159 -> 3000811051 | D162: ='Consumo Médio - Clientes'!AX159 -> 564.66667 | E162: =F162/D162 -> 0.94622196 | F162: =SUM(H162*$H$2,I162*$I$2,J162*$J$2,$K$2*K162,$L$2*L162,M162*$M$2,N162*$N$2,O162*$O$2) -> 534.3 | G162: ='Consumo Médio - Clientes'!AY156 -> 0 | H162: 0.01 | I162: 0 | J162: 0 | K162: 0 | L162: 0 | M162: 0 | N162: 0 | O162: 0
F163: TOTAL | H163: =SUM(H5:H162) -> 1.037 | I163: =SUM(I5:I162) -> 0.5235 | J163: =SUM(J5:J162) -> 1 | K163: =SUM(K5:K162) -> 1 | L163: =SUM(L5:L162) -> 1 | M163: =SUM(M5:M162) -> 1 | N163: =SUM(N5:N162) -> 1 | O163: =SUM(O5:O162) -> 1

Sheet Consumo Médio - Clientes
A1: Cliente | B1: Nº Cliente | C1: UC | D1: 43617 | E1: 43647 | F1: 43678 | G1: 43709 | H1: 43739 | I1: 43770 | J1: 43800 | K1: 43831 | L1: 43862 | M1: 43891 | N1: 43922 | O1: 43952 | P1: 43983 | Q1: 44013 | R1: 44044 | S1: 44075 | T1: 44105 | U1: 44136 | V1: 44166 | W1: 44197 | X1: 44228 | Y1: 44256 | Z1: 44287 | AA1: 44317 | AB1: 44348 | AC1: 44378 | AD1: 44409 | AE1: 44440 | AF1: 44470 | AG1: 44501 | AH1: 44531 | AI1: 44562 | AJ1: 44593 | AK1: 44621 | AL1: 44652 | AM1: 44682 | AN1: 44713 | AO1: 44743 | AP1: 44774 | AQ1: 44805 | AR1: 44835 | AS1: 44866 | AT1: 44896 | AU1: 44927 | AV1: 44958 | AW1: 44986 | AX1: Média Trimestral | AY1: Saldo GD | AZ1: Competência | BA1: Vencimento | BB1: Faturar
A2: Lucile Confecções LTDA | B2: 7005713839 | C2: 3003858507 | D2: 1246 | E2: 1081 | F2: 1184 | G2: 1549 | H2: 2045 | I2: 4017 | J2: 2386 | K2: 4239 | L2: 2854 | M2: 3208 | N2: 1048 | O2: 1313 | P2: 1174 | Q2: 799 | R2: 952 | S2: 2085 | T2: 4218 | U2: 2922 | V2: 2964 | W2: 2806 | X2: 2186 | Y2: 1712 | Z2: 1123 | AA2: 1099 | AB2: 1881 | AC2: 1190 | AD2: 1279 | AE2: 3083 | AF2: 3273 | AG2: 2724 | AH2: 3490 | AI2: 3357 | AJ2: 3625 | AK2: 4187 | AL2: 3840 | AM2: 2478 | AN2: 817 | AO2: 601 | AP2: 638 | AQ2: 686 | AR2: 1216 | AS2: 1335 | AT2: 1317 | AU2: 2367 | AV2: 3056 | AW2: 3612 | AX2: 3308 | AY2: 0 | BE2: Jan | BF2: fev | BG2: Mar | BH2: Abr | BI2: Mai | BJ2: Jun | BK2: Jul | BL2: Ago | BM2: Set | BN2: Out | BO2: Nov | BP2: Dez
A3: CLL Hotel e Turismo | B3: 7008528502 | C3: 3001084033 | D3: 7160 | E3: 6520 | F3: 6840 | G3: 7440 | H3: 6920 | I3: 6920 | J3: 7240 | K3: 6560 | L3: 7440 | M3: 7440 | N3: 5640 | O3: 4880 | P3: 5080 | Q3: 4840 | R3: 6520 | S3: 6120 | T3: 5720 | U3: 7480 | V3: 6680 | W3: 6680 | X3: 5680 | Y3: 5760 | Z3: 3760 | AA3: 4280 | AB3: 5800 | AC3: 5480 | AD3: 5480 | AE3: 5280 | AF3: 5760 | AG3: 5560 | AH3: 6600 | AI3: 6400 | AJ3: 7160 | AK3: 6960 | AL3: 7080 | AM3: 6800 | AN3: 6760 | AO3: 6280 | AP3: 5560 | AQ3: 6360 | AR3: 7440 | AS3: 7240 | AT3: 7960 | AU3: 5880 | AV3: 7560 | AW3: 7640 | AX3: 7707 | AY3: 19766 | AZ3: Abril | BA3: 45049 | BB3: 45036 | BC3: Usina - Fazenda Vale do Sol | BD3: 3013497957 | BE3: 53904 | BF3: 52408 | BG3: 52317 | BH3: 48122 | BI3: 50739 | BJ3: 48737 | BK3: 52874 | BL3: 56271 | BM3: 51096 | BN3: 53430 | BO3: 45995 | BP3: 51054
A4: Academia Planeta Corpo | B4: 7005369021 | C4: 3011373971 | D4: 440 | E4: 600 | F4: 680 | G4: 760 | H4: 560 | I4: 520 | J4: 320 | K4: 440 | L4: 280 | M4: 320 | N4: 440 | O4: 0 | P4: 0 | Q4: 0 | R4: 0 | S4: 320 | T4: 280 | U4: 360 | V4: 280 | W4: 400 | X4: 320 | Y4: 280 | Z4: 0 | AA4: 400 | AB4: 480 | AC4: 480 | AD4: 600 | AE4: 560 | AF4: 480 | AG4: 560 | AH4: 480 | AI4: 480 | AJ4: 440 | AK4: 560 | AL4: 560 | AM4: 680 | AN4: 840 | AO4: 800 | AP4: 760 | AQ4: 840 | AR4: 920 | AS4: 360 | AT4: 680 | AU4: 800 | AV4: 480 | AW4: 440 | AX4: 467 | AY4: 1359 | AZ4: Abril | BA4: 45063 | BB4: 45044
A5: MD Predial | B5: 7005492088 | C5: 3001449459 | D5: 960 | E5: 920 | F5: 1120 | G5: 1040 | H5: 1120 | I5: 1240 | J5: 1000 | K5: 1120 | L5: 1200 | M5: 1360 | N5: 1080 | O5: 1040 | P5: 1320 | Q5: 960 | R5: 1240 | S5: 1280 | T5: 1480 | U5: 1320 | V5: 1400 | W5: 1160 | X5: 960 | Y5: 1000 | Z5: 1160 | AA5: 960 | AB5: 960 | AC5: 1000 | AD5: 1040 | AE5: 1160 | AF5: 840 | AG5: 760 | AH5: 720 | AI5: 720 | AJ5: 720 | AK5: 720 | AL5: 800 | AM5: 800 | AN5: 720 | AO5: 880 | AP5: 680 | AQ5: 800 | AR5: 1000 | AS5: 840 | AT5: 880 | AU5: 840 | AV5: 760 | AX5: 1440 | AY5: 0
A6: MD Predial | B6: 7005492088 | C6: 3011504476 | D6: 1560 | E6: 1280 | F6: 1360 | G6: 1680 | H6: 1680 | I6: 2920 | J6: 1960 | K6: 2280 | L6: 2480 | M6: 2240 | N6: 1480 | O6: 1280 | P6: 1240 | Q6: 1160 | R6: 1360 | S6: 1400 | T6: 2480 | U6: 2320 | V6: 3320 | W6: 2640 | X6: 2160 | Y6: 2120 | Z6: 2320 | AA6: 1520 | AB6: 1640 | AC6: 1200 | AD6: 1200 | AE6: 2040 | AF6: 2040 | AG6: 2080 | AH6: 2280 | AI6: 2600 | AJ6: 2520 | AK6: 3240 | AL6: 2960 | AM6: 1840 | AN6: 1600 | AO6: 1480 | AP6: 1440 | AQ6: 1720 | AR6: 2280 | AS6: 2000 | AT6: 2160 | AU6: 2120 | AV6: 2680 | AW6: 1589 | AX6: 1867 | AY6: 127
A7: MD Predial | B7: 7005492088 | C7: 3014340686 | T7: 3388 | U7: 3162 | V7: 2869 | W7: 3865 | X7: 2686 | Y7: 2154 | Z7: 2233 | AA7: 2095 | AB7: 1581 | AC7: 2146 | AD7: 2397 | AE7: 2247 | AF7: 1782 | AG7: 1670 | AH7: 1720 | AI7: 1677 | AJ7: 1812 | AK7: 1870 | AL7: 1995 | AM7: 2283 | AN7: 1309 | AO7: 1829 | AP7: 1449 | AQ7: 1792 | AR7: 1559 | AS7: 1660 | AT7: 1639 | AU7: 1635 | AV7: 1558 | AW7: 1406 | AX7: 1447 | AY7: 0
A8: Fazenda Terra Mirante | B8: 7202158396 | C8: 3002906325 | I8: 404 | J8: 297 | K8: 358 | L8: 315 | M8: 322 | N8: 340 | O8: 340 | P8: 401 | Q8: 307 | R8: 402 | S8: 347 | T8: 457 | U8: 350 | V8: 350 | W8: 350 | X8: 350 | Y8: 350 | Z8: 433 | AA8: 402 | AB8: 417 | AC8: 407 | AD8: 454 | AE8: 373 | AF8: 411 | AG8: 720 | AH8: 387 | AI8: 387 | AJ8: 377 | AK8: 462 | AL8: 374 | AM8: 351 | AN8: 413 | AO8: 358 | AP8: 344 | AQ8: 429 | AR8: 407 | AS8: 389 | AT8: 434 | AU8: 389 | AV8: 375 | AW8: 404 | AX8: 388 | AY8: 0
A9: Irmãs Martins Andrade LTDA-ME | B9: 7005723073 | C9: 3002906806 | D9: 2263 | E9: 1989 | F9: 2277 | G9: 2031 | H9: 1941 | I9: 2268 | J9: 2117 | K9: 2058 | L9: 2364 | M9: 2129 | N9: 1606 | O9: 1762 | P9: 1730 | Q9: 1587 | R9: 1999 | S9: 1958 | T9: 2118 | U9: 2132 | V9: 1331 | W9: 2162 | X9: 1983 | Y9: 2200 | Z9: 2071 | AA9: 1894 | AB9: 2236 | AC9: 1987 | AD9: 2075 | AE9: 2317 | AF9: 2086 | AG9: 2202 | AH9: 2036 | AI9: 1910 | AJ9: 2143 | AK9: 2219 | AL9: 1944 | AM9: 2110 | AN9: 2194 | AO9: 2072 | AP9: 1989 | AQ9: 2421 | AR9: 2164 | AS9: 2064 | AT9: 2353 | AU9: 2152 | AV9: 2098 | AW9: 2393 | AX9: 2262 | AY9: 4764 | AZ9: Abril | BA9: 45063 | BB9: 45044
A10: Supermercado Bela Vista | B10: 7009098124 | C10: 3003388708 | D10: 5830 | E10: 4757 | F10: 4753 | G10: 5481 | H10: 5249 | I10: 6055 | J10: 5647 | K10: 6105 | L10: 6355 | M10: 6094 | N10: 5388 | O10: 6589 | P10: 5750 | Q10: 5874 | R10: 6723 | S10: 5634 | T10: 6380 | U10: 7074 | V10: 6620 | W10: 7928 | X10: 6492 | Y10: 6326 | Z10: 7223 | AA10: 5740 | AB10: 5617 | AC10: 5318 | AD10: 5797 | AE10: 5391 | AF10: 6048 | AG10: 5196 | AH10: 4642 | AI10: 5976 | AJ10: 5269 | AK10: 4911 | AL10: 5180 | AM10: 4998 | AN10: 4687 | AO10: 4880 | AP10: 4113 | AQ10: 4492 | AR10: 4935 | AS10: 4949 | AT10: 5240 | AU10: 5156 | AV10: 5311 | AW10: 5642 | AX10: 5293 | AY10: 2658 | AZ10: Abril | BA10: 45039 | BB10: 45027
A11: Supermercado Bela Vista | B11: 7009098124 | C11: 3010494037 | D11: 3320 | E11: 2840 | F11: 3000 | G11: 2880 | H11: 2600 | I11: 3360 | J11: 3000 | K11: 3200 | L11: 3280 | M11: 1560 | N11: 800 | O11: 920 | P11: 0 | Q11: 0 | R11: 0 | S11: 0 | T11: 0 | U11: 0 | V11: 0 | W11: 0 | X11: 0 | Y11: 0 | Z11: 0 | AA11: 0 | AB11: 0 | AC11: 0 | AD11: 1080 | AE11: 12320 | AF11: 15800 | AG11: 14120 | AH11: 15280 | AI11: 4880 | AJ11: 26960 | AK11: 13680 | AL11: 14040 | AM11: 13520 | AN11: 11880 | AO11: 12360 | AP11: 10520 | AQ11: 10920 | AR11: 11520 | AS11: 12200 | AT11: 14080 | AU11: 15600 | AV11: 12640 | AW11: 14880 | AX11: 13467 | AY11: 8076 | AZ11: Abril | BA11: 45039 | BB11: 45027
A12: Supermercado Tia Lia | B12: 7005719624 | C12: 3001268572 | D12: 4590 | E12: 3124 | F12: 4253 | G12: 3269 | H12: 3414 | I12: 3814 | J12: 3437 | K12: 3922 | L12: 4078 | M12: 4227 | N12: 4622 | O12: 3755 | P12: 3643 | Q12: 3284 | R12: 3940 | S12: 3522 | T12: 1700 | U12: 1700 | V12: 1700 | W12: 1700 | X12: 1700 | Y12: 1700 | Z12: 1700 | AA12: 1700 | AB12: 3969 | AC12: 3557 | AD12: 3789 | AE12: 4493 | AF12: 4292 | AG12: 4059 | AH12: 4214 | AI12: 4377 | AJ12: 4185 | AK12: 4195 | AL12: 4522 | AM12: 4187 | AN12: 4519 | AO12: 4038 | AP12: 4312 | AQ12: 4400 | AR12: 4364 | AS12: 4073 | AT12: 4677 | AU12: 4585 | AV12: 4276 | AX12: 3097 | AY12: 0
A13: A M Lage | B13: 7005623640 | C13: 3002176022 | D13: 6392 | E13: 6030 | F13: 6554 | G13: 7210 | H13: 8151 | I13: 9324 | J13: 7625 | K13: 9372 | L13: 7768 | M13: 7818 | N13: 5646 | O13: 4484 | P13: 4853 | Q13: 5044 | R13: 5315 | S13: 5749 | T13: 8479 | U13: 7719 | V13: 7737 | W13: 9244 | X13: 8300 | Y13: 7206 | Z13: 7512 | AA13: 6695 | AB13: 6704 | AC13: 6486 | AD13: 6130 | AE13: 7771 | AF13: 8228 | AG13: 6255 | AH13: 6377 | AI13: 6163 | AJ13: 6120 | AK13: 6394 | AL13: 6484 | AM13: 5759 | AN13: 6007 | AO13: 5273 | AP13: 5917 | AQ13: 6615 | AR13: 6858 | AS13: 6276 | AT13: 7010 | AU13: 6369 | AV13: 6131 | AW13: 7062 | AX13: 6475 | AY13: 8587
A14: Contabilidade Rocha | B14: 7202048247 | C14: 3003586967 | F14: 97 | G14: 188 | H14: 178 | I14: 204 | J14: 170 | K14: 209 | L14: 193 | M14: 169 | N14: 169 | O14: 229 | P14: 172 | Q14: 165 | R14: 207 | S14: 165 | T14: 195 | U14: 185 | V14: 184 | W14: 223 | X14: 176 | Y14: 195 | Z14: 223 | AA14: 191 | AB14: 227 | AC14: 242 | AD14: 200 | AE14: 193 | AF14: 199 | AG14: 241 | AH14: 228 | AI14: 272 | AJ14: 253 | AK14: 252 | AL14: 250 | AM14: 229 | AN14: 241 | AO14: 235 | AP14: 241 | AQ14: 276 | AR14: 281 | AS14: 238 | AT14: 261 | AU14: 266 | AV14: 203 | AW14: 322 | AX14: 289 | AY14: 151
A15: Contabilidade Rocha | B15: 7202048247 | C15: 3000881551 | F15: 791 | G15: 1204 | H15: 1197 | I15: 1238 | J15: 1119 | K15: 1203 | L15: 1207 | M15: 1226 | N15: 1173 | O15: 1194 | P15: 1106 | Q15: 978 | R15: 1158 | S15: 1103 | T15: 1129 | U15: 1175 | V15: 1120 | W15: 1199 | X15: 1185 | Y15: 1358 | Z15: 1357 | AA15: 1262 | AB15: 1484 | AC15: 1330 | AD15: 1435 | AE15: 1349 | AF15: 1308 | AG15: 1304 | AH15: 1253 | AI15: 1558 | AJ15: 1259 | AK15: 1294 | AL15: 1454 | AM15: 1501 | AN15: 1501 | AO15: 1486 | AP15: 1405 | AQ15: 1386 | AR15: 1321 | AS15: 1417 | AT15: 1442 | AU15: 1406 | AV15: 1407 | AW15: 1460 | AX15: 1514 | AY15: 0
A16: Hotel Itabira | B16: 7005634342 | C16: 3002906805 | D16: 1680 | E16: 1720 | F16: 1760 | G16: 1760 | H16: 1680 | I16: 1920 | J16: 1560 | K16: 1680 | L16: 2600 | M16: 1680 | N16: 2240 | O16: 1360 | P16: 1560 | Q16: 1760 | R16: 2680 | S16: 2520 | T16: 3160 | U16: 2800 | V16: 1840 | W16: 2680 | X16: 2960 | Y16: 3320 | Z16: 3120 | AA16: 2400 | AB16: 2440 | AC16: 2720 | AD16: 3040 | AE16: 3160 | AF16: 3120 | AG16: 3080 | AH16: 2560 | AI16: 2000 | AJ16: 2400 | AK16: 2600 | AL16: 2560 | AM16: 2640 | AN16: 2600 | AO16: 2400 | AP16: 2320 | AQ16: 2400 | AR16: 2360 | AS16: 3000 | AT16: 3040 | AU16: 2480 | AV16: 2640 | AW16: 2880 | AX16: 2707 | AY16: 3932 | AZ16: Abril | BA16: 45063 | BB16: 45074
A17: Sindicato Metabase Itabira | B17: 7000047224 | C17: 3001450247 | D17: 2669 | E17: 2402 | F17: 2575 | G17: 3342 | H17: 3646 | I17: 5223 | J17: 3518 | K17: 5056 | L17: 4119 | M17: 3686 | N17: 1949 | O17: 1421 | P17: 1676 | Q17: 1664 | R17: 2026 | S17: 2162 | T17: 3512 | U17: 3140 | V17: 3231 | W17: 4515 | X17: 4033 | Y17: 2909 | Z17: 2052 | AA17: 2058 | AB17: 2396 | AC17: 2012 | AD17: 2085 | AE17: 2865 | AF17: 3438 | AG17: 3211 | AH17: 3408 | AI17: 2532 | AJ17: 3066 | AK17: 3763 | AL17: 3574 | AM17: 2361 | AN17: 1798 | AO17: 1680 | AP17: 1946 | AQ17: 2006 | AR17: 2731 | AS17: 2673 | AT17: 2628 | AU17: 2563 | AV17: 2565 | AW17: 2524 | AX17: 2996 | AY17: 604
A18: Orbis Energia | B18: 7202360028 | C18: 3012107385 | D18: 300 | E18: 300 | F18: 300 | G18: 300 | H18: 300 | I18: 300 | J18: 300 | K18: 300 | L18: 300 | M18: 300 | N18: 300 | O18: 300 | P18: 300 | Q18: 300 | R18: 300 | S18: 300 | T18: 300 | U18: 411 | V18: 428 | W18: 477 | X18: 450 | Y18: 313 | Z18: 363 | AA18: 251 | AB18: 352 | AC18: 547 | AD18: 647 | AE18: 467 | AF18: 701 | AG18: 593 | AH18: 657 | AI18: 583 | AJ18: 646 | AK18: 452 | AL18: 197 | AM18: 429 | AN18: 357 | AO18: 397 | AP18: 362 | AQ18: 415 | AR18: 480 | AS18: 464 | AT18: 497 | AU18: 441 | AV18: 526 | AW18: 668 | AX18: 534 | AY18: 3139
A19: Funcesi | B19: 7201768092 | C19: 3009018668 | D19: 28467 | E19: 28350 | F19: 30683 | G19: 31733 | H19: 36167 | I19: 33950 | J19: 27300 | K19: 18317 | L19: 31267 | M19: 33367 | N19: 31033 | O19: 34650 | P19: 35000 | Q19: 35000 | R19: 35000 | S19: 20000 | T19: 20000 | U19: 11600 | V19: 11600 | W19: 12150 | X19: 11800 | Y19: 11600 | Z19: 11450 | AA19: 13150 | AB19: 13850 | AC19: 13850 | AD19: 16250 | AE19: 30306 | AF19: 27807 | AG19: 27560 | AH19: 25015 | AI19: 25115 | AJ19: 24002 | AK19: 32034 | AL19: 30154 | AM19: 31283 | AN19: 27484 | AO19: 0 | AX19: #DIV/0! | AY19: 0
A20: WB JS Comunicação | B20: 7010498067 | C20: 3013027271 | N20: 1880 | O20: 1560 | P20: 1920 | Q20: 2120 | R20: 2480 | S20: 2840 | T20: 3320 | U20: 4520 | V20: 3360 | W20: 4720 | X20: 2880 | Y20: 2920 | Z20: 2840 | AA20: 2160 | AB20: 1680 | AC20: 2280 | AD20: 1920 | AE20: 2080 | AF20: 2600 | AG20: 2520 | AH20: 2720 | AI20: 4480 | AJ20: 5320 | AK20: 2920 | AL20: 2480 | AM20: 2120 | AN20: 1920 | AO20: 1880 | AP20: 1600 | AQ20: 2160 | AR20: 2120 | AS20: 2080 | AT20: 2120 | AU20: 4600 | AV20: 2840 | AW20: 2880 | AX20: 2880 | AY20: 0 | AZ20: Abril | BA20: 45047 | BB20: 45027
A21: ART Pão de Itabira | B21: 7005530163 | C21: 3003562994 | N21: 4027 | O21: 3618 | P21: 3214 | Q21: 3814 | R21: 4394 | S21: 4063 | T21: 4281 | U21: 4555 | V21: 4560 | W21: 4696 | X21: 4036 | Y21: 4610 | Z21: 4644 | AA21: 3829 | AB21: 4220 | AC21: 3983 | AD21: 4405 | AE21: 4636 | AF21: 4094 | AG21: 3972 | AH21: 3990 | AI21: 4259 | AJ21: 3533 | AK21: 4136 | AL21: 4242 | AM21: 4374 | AN21: 3762 | AO21: 3932 | AP21: 3808 | AQ21: 4268 | AR21: 3798 | AS21: 3772 | AT21: 4392 | AU21: 3761 | AV21: 3168 | AW21: 3828 | AX21: 3344 | AY21: 4862 | AZ21: Abril | BA21: 45049 | BB21: 45036
A22: Hortifruti QueBom | B22: 7202402563 | C22: 3006700739 | W22: 5450 | X22: 5169 | Y22: 5032 | Z22: 4835 | AA22: 3814 | AB22: 4439 | AC22: 3840 | AD22: 4163 | AE22: 4852 | AF22: 4573 | AG22: 4633 | AH22: 4226 | AI22: 4402 | AJ22: 4407 | AK22: 5001 | AL22: 4702 | AM22: 4172 | AN22: 4364 | AO22: 3782 | AP22: 4115 | AQ22: 4019 | AR22: 4133 | AS22: 3984 | AT22: 4338 | AU22: 4096 | AV22: 3880 | AW22: 4703 | AX22: 4243 | AY22: 2163
A23: Maria do Carmo Oliveira Olimpio | B23: 7202760807 | C23: 3012940288 | Y23: 2300 | Z23: 2825 | AA23: 1947 | AB23: 1939 | AC23: 1462 | AD23: 1822 | AE23: 2491 | AF23: 2045 | AG23: 1883 | AH23: 2057 | AI23: 2032 | AJ23: 2070 | AK23: 2514 | AL23: 2551 | AM23: 1624 | AN23: 1461 | AO23: 1341 | AP23: 1749 | AQ23: 1878 | AR23: 2216 | AS23: 1892 | AT23: 2038 | AU23: 2041 | AV23: 2413 | AW23: 2408 | AX23: 2437 | AY23: 181
A24: Jordana de Castro Comercio | B24: 7202482231 | C24: 3004607095 | AD24: 263 | AE24: 325 | AF24: 576 | AG24: 255 | AH24: 388 | AI24: 499 | AJ24: 585 | AK24: 564 | AL24: 703 | AM24: 469 | AN24: 273 | AO24: 273 | AP24: 251 | AQ24: 194 | AR24: 320 | AS24: 418 | AT24: 388 | AU24: 451 | AV24: 508 | AW24: 645 | AX24: 559 | AY24: 113 | AZ24: Abril | BA24: 45049 | BB24: 45036
A25: Jordana de Castro Comercio | B25: 7202482231 | C25: 3005534144 | AE25: 102 | AF25: 239 | AG25: 217 | AH25: 243 | AI25: 284 | AJ25: 289 | AK25: 300 | AL25: 304 | AM25: 283 | AN25: 196 | AO25: 197 | AP25: 175 | AQ25: 266 | AR25: 191 | AS25: 192 | AT25: 223 | AU25: 230 | AV25: 221 | AW25: 281 | AX25: 258 | AY25: 1179 | AZ25: Abril | BA25: 45052 | BB25: 45036
A26: Dr Redes (Consórcio) | B26: 7201768092 | C26: 3012189878 | AC26: 490 | AD26: 430 | AE26: 523 | AF26: 592 | AG26: 606 | AH26: 595 | AI26: 620 | AJ26: 718 | AK26: 823 | AL26: 749 | AM26: 750 | AN26: 741 | AO26: 543 | AP26: 603 | AQ26: 539 | AR26: 673 | AS26: 681 | AT26: 162 | AU26: 780 | AV26: 872 | AW26: 906 | AX26: 879 | AY26: 0
A27: Sanati (Consórcio) | B27: 7201768092 | C27: 3001450194 | AG27: 29 | AH27: 26 | AI27: 77 | AJ27: 307 | AK27: 450 | AL27: 450 | AM27: 450 | AN27: 458 | AO27: 437 | AP27: 460 | AQ27: 512 | AR27: 458 | AS27: 438 | AT27: 476 | AU27: 440 | AV27: 529 | AW27: 571 | AX27: 542 | AY27: 386 | AZ27: Abril | BA27: 45057 | BB27: 45036
A28: Renato (Orbis) | B28: 7202360028 | C28: 3014183803 | AL28: 250 | AM28: 223 | AN28: 238 | AO28: 230 | AP28: 228 | AQ28: 257 | AR28: 288 | AS28: 271 | AT28: 349 | AU28: 330 | AV28: 346 | AW28: 396 | AX28: 380 | AY28: 217
A29: Somatis_Clinica Fisioterapia | B29: 7005466339 | C29: 3013791114 | AN29: 150 | AO29: 184 | AP29: 143 | AQ29: 174 | AR29: 337 | AS29: 266 | AT29: 295 | AU29: 297 | AV29: 432 | AW29: 399 | AX29: 400 | AY29: 1163
A30: Somatis_Clinica Fisioterapia | B30: 7005466339 | C30: 3002619862 | AN30: 290 | AO30: 139 | AP30: 200 | AQ30: 222 | AR30: 400 | AS30: 452 | AT30: 531 | AU30: 415 | AV30: 804 | AW30: 1072 | AX30: 882 | AY30: 0
A31: Lanza Magalhães_Dr. Pet | B31: 7200135835 | C31: 3001450251 | AB31: 339 | AC31: 289 | AD31: 288 | AE31: 470 | AF31: 475 | AG31: 386 | AH31: 366 | AI31: 390 | AJ31: 433 | AK31: 541 | AL31: 547 | AM31: 390 | AN31: 336 | AO31: 332 | AP31: 378 | AQ31: 468 | AR31: 567 | AS31: 536 | AT31: 613 | AU31: 645 | AV31: 694 | AW31: 875 | AX31: 770 | AY31: 0
A32: Celso Matozinho_Serra 1 (Consórcio) | B32: 7201768092 | C32: 3012262751 | AN32: 500 | AO32: 236 | AP32: 264 | AQ32: 610 | AR32: 373 | AS32: 400 | AT32: 262 | AU32: 340 | AV32: 348 | AW32: 156 | AX32: 235 | AY32: 913
A33: Celso Matozinho_Serra 2 (Consórcio) | B33: 7201768092 | C33: 3007395349 | AN33: 400 | AO33: 0 | AP33: 500 | AQ33: 249 | AR33: 277 | AS33: 300 | AT33: 156 | AU33: 211 | AV33: 233 | AW33: 259 | AX33: 247 | AY33: 686
A34: Celso Matozinho_BH (Consórcio) | B34: 7201768092 | C34: 3001780367 | AN34: 150 | AO34: 189 | AP34: 208 | AQ34: 236 | AR34: 223 | AS34: 166 | AT34: 154 | AU34: 99 | AV34: 186 | AW34: 222 | AX34: 203 | AY34: 1782
A35: Celso Matozinho_Itabira (Consórcio) | B35: 7201768092 | C35: 3000914060 | AN35: 400 | AO35: 544 | AP35: 361 | AQ35: 355 | AR35: 475 | AS35: 386 | AT35: 529 | AU35: 356 | AV35: 436 | AW35: 464 | AX35: 434 | AY35: 0
A36: Carlos Roberto | B36: 7005439127 | C36: 3012512271 | AB36: 412 | AC36: 350 | AD36: 394 | AE36: 410 | AF36: 395 | AG36: 319 | AH36: 313 | AI36: 459 | AJ36: 418 | AK36: 415 | AL36: 389 | AM36: 453 | AN36: 485 | AO36: 315 | AP36: 307 | AQ36: 387 | AR36: 348 | AS36: 381 | AT36: 406 | AU36: 473 | AV36: 468 | AW36: 541 | AX36: 489 | AY36: 51 | AZ36: Abril | BA36: 45049 | BB36: 45036
A37: Simonica Rodrigues | B37: 7200317399 | C37: 3011377412 | AC37: 978 | AD37: 1194 | AE37: 1391 | AF37: 1728 | AG37: 1384 | AH37: 1202 | AI37: 1476 | AJ37: 1025 | AK37: 1182 | AL37: 1205 | AM37: 1004 | AN37: 897 | AO37: 1006 | AP37: 1049 | AQ37: 1069 | AR37: 1254 | AS37: 1180 | AT37: 1106 | AU37: 1359 | AV37: 1232 | AW37: 1393 | AX37: 1353 | AY37: 0 | AZ37: Abril | BA37: 45054 | BB37: 45036
A38: Hortifruti QueBom | B38: 7202402563 | C38: 3012307446 | AK38: 9038 | AL38: 5435 | AM38: 5505 | AN38: 5499 | AO38: 4952 | AP38: 4971 | AQ38: 5017 | AR38: 3834 | AS38: 3163 | AT38: 3830 | AU38: 3327 | AV38: 3278 | AW38: 3661 | AX38: 2547 | AY38: 4797 | AZ38: Abril | BA38: 45057 | BB38: 45036
A39: Padaria Bouzada I LTDA | B39: 7202646947 | C39: 3004256972 | AC39: 5456 | AD39: 7504 | AE39: 8051 | AF39: 8046 | AG39: 7673 | AH39: 9266 | AI39: 9188 | AJ39: 9128 | AK39: 9842 | AL39: 8327 | AM39: 9309 | AN39: 8770 | AO39: 8416 | AP39: 8243 | AQ39: 9570 | AR39: 8795 | AS39: 8479 | AT39: 10474 | AU39: 9945 | AV39: 9440 | AW39: 10750 | AX39: 9946 | AY39: 3275 | AZ39: Abril | BA39: 45043 | BB39: 45036
A40: Fabrica Gelo Norma | B40: 7200746623 | C40: 3002725236 | AE40: 100 | AF40: 492 | AG40: 2800 | AH40: 7760 | AI40: 640 | AJ40: 2320 | AK40: 4720 | AL40: 5840 | AM40: 5640 | AN40: 5400 | AO40: 5280 | AP40: 5600 | AQ40: 5920 | AR40: 8040 | AS40: 6640 | AT40: 11520 | AU40: 8520 | AV40: 11320 | AW40: 7400 | AX40: 7720 | AY40: 0
A41: MBLB Acabamentos Ltda | B41: 7005602485 | C41: 3003245697 | AN41: 1367 | AO41: 1136 | AP41: 1300 | AQ41: 1385 | AT41: 1411 | AU41: 1344 | AX41: 1614 | AY41: 10
A42: Cervejaria Portal da Canastra Ltda | B42: 7202649326 | C42: 3014018953 | AN42: 2000 | AO42: 1560 | AP42: 1460 | AQ42: 1800 | AR42: 1480 | AS42: 1480 | AT42: 1800 | AU42: 1720 | AV42: 1880 | AX42: 2480 | AY42: 0
A43: Faculdade Maximum LTDA | B43: 7010221388 | C43: 3001348433 | AN43: 529 | AO43: 412 | AP43: 521 | AQ43: 583 | AR43: 796 | AS43: 824 | AT43: 867 | AU43: 636 | AV43: 1007 | AW43: 1182 | AX43: 1068 | AY43: 0 | AZ43: Abril | BA43: 45057 | BB43: 45044
A44: Otávio Reis Oliveira Pereira | B44: 7010540003 | C44: 3010642300 | AN44: 388 | AO44: 361 | AP44: 372 | AQ44: 405 | AR44: 423 | AS44: 398 | AT44: 508 | AU44: 380 | AV44: 425 | AW44: 539 | AX44: 445 | AY44: 431 | AZ44: Abril | BA44: 45043 | BB44: 45036
A45: Ortecon Acessoria LTDA | B45: 7010076392 | C45: 3011515927 | AM45: 1588 | AN45: 2330 | AO45: 2080 | AP45: 1899 | AQ45: 2203 | AR45: 1652 | AS45: 1293 | AT45: 883 | AU45: 864 | AV45: 1147 | AW45: 1301 | AX45: 1271 | AY45: 0 | AZ45: Abril | BA45: 45041 | BB45: 45027
A46: Zilda Soares da Costa Ltda | C46: 3000886634 | AO46: 2320 | AP46: 2183 | AQ46: 2673 | AR46: 2233 | AS46: 2364 | AT46: 2500 | AU46: 2310 | AV46: 2369 | AX46: 2638 | AY46: 0 | AZ46: Abril | BA46: 45048 | BB46: 45036
A47: Israel Bernardo de Assis Silva | C47: 3000914420 | AO47: 579 | AP47: 588 | AQ47: 691 | AR47: 801 | AS47: 455 | AT47: 669 | AU47: 210 | AV47: 187 | AW47: 355 | AX47: 181 | AY47: 1310
A48: Recuperadora de Veículos UDIA | C48: 3005437596 | AO48: 2320 | AP48: 2960 | AQ48: 2560 | AT48: 2960 | AU48: 2640 | AX48: 1853 | AY48: 2510
A49: Laticínios Moedense | B49: 7005258399 | C49: 3000184598 | AO49: 1899 | AP49: 1125 | AQ49: 2165 | AT49: 3029 | AU49: 2630 | AV49: 2561 | AW49: 3084 | AX49: 2861 | AY49: 1996 | AZ49: Abril | BA49: 45038 | BB49: 45027
A50: Laticínios Moedense | B50: 7005258399 | C50: 3000227098 | AO50: 3957 | AP50: 4671 | AQ50: 4296 | AT50: 5103 | AU50: 4604 | AV50: 4229 | AW50: 5124 | AX50: 4561 | AY50: 9716
A51: Bernardo Bousada Rodrigues (INATIVO) | B51: 7202855145 | C51: 3003168714 | AO51: 9800 | AP51: 9640 | AQ51: 10400 | AT51: 11200 | AU51: 11040 | AV51: 10160 | AX51: 10027 | AY51: 0
A52: Diogo Pitol Cangussu | B52: 7008603422 | C52: 3002421654 | AO52: 1010 | AP52: 1042 | AQ52: 1840 | AT52: 1315 | AU52: 1132 | AV52: 1152 | AW52: 968 | AX52: 1055 | AY52: 2096 | AZ52: Abril | BA52: 45073 | BB52: 45044
A53: Yago Vidal Martins da Costa | B53: 7201100845 | C53: 3007592986 | AO53: 180 | AP53: 193 | AQ53: 205 | AT53: 324 | AU53: 238 | AV53: 192 | AW53: 260 | AX53: 255 | AY53: 75
A54: Euripedes Duarte da Costa | B54: 7005407157 | C54: 3002429190 | AN54: 342 | AO54: 252 | AP54: 324 | AT54: 466 | AU54: 394 | AV54: 467 | AW54: 481 | AX54: 463 | AY54: 145
A55: Euripedes Duarte da Costa | B55: 7005407157 | C55: 3004338248 | AN55: 117 | AO55: 106 | AP55: 108 | AT55: 143 | AU55: 224 | AV55: 129 | AW55: 136 | AX55: 134 | AY55: 178 | AZ55: Abril | BA55: 45055 | BB55: 45044
A56: AD Soluções Educacionais LTDA | B56: 7202295461 | C56: 3005563221 | AN56: 1238 | AO56: 1118 | AP56: 820 | AU56: 2000 | AV56: 1501 | AW56: 3504 | AX56: 2335 | AY56: 0 | AZ56: Abril | BA56: 45068 | BB56: 45044
A57: Fernanda Gil de Oliveira Andrade | B57: 7003275088 | C57: 3014052549 | AO57: 488 | AP57: 489 | AQ57: 436 | AT57: 677 | AU57: 574 | AV57: 602 | AX57: 690 | AY57: 23
A58: Jesimiel de Oliveira Neves | B58: 7010040729 | C58: 3010470206 | AM58: 144 | AN58: 122 | AO58: 112 | AT58: 199 | AU58: 191 | AV58: 220 | AW58: 236 | AX58: 222 | AY58: 87
A59: Alexandre Rodrigues Sirimarco | C59: 3001346174 | AT59: 270 | AU59: 353 | AV59: 304 | AW59: 345 | AX59: 298 | AY59: 159 | AZ59: Abril | BA59: 45063 | BB59: 45044
A60: Off Limits Ind Componentes Automotivos | B60: 7005542671 | C60: 3003413089 | AO60: 5040 | AP60: 4720 | AQ60: 4240 | AT60: 4960 | AU60: 1840 | AV60: 4400 | AW60: 4320 | AX60: 4533 | AY60: 11041 | AZ60: Abril | BA60: 45052 | BB60: 45036
A61: AC Baruk Esfiharia Ltda | B61: 7008805822 | C61: 3004493730 | AP61: 394 | AQ61: 435 | AR61: 636 | AT61: 690 | AU61: 717 | AV61: 723 | AW61: 487 | AX61: 662 | AY61: 114
A62: Sonia Maria Favaro Lopes | B62: 7009356799 | C62: 3005316449 | AO62: 321 | AP62: 300 | AQ62: 319 | AT62: 281 | AU62: 332 | AV62: 279 | AW62: 319 | AX62: 290 | AY62: 192 | AZ62: Abril | BA62: 45027 | BB62: 45036
A63: Ulisse Eduardo Barros | B63: 7003542687 | C63: 3003930453 | AP63: 264 | AQ63: 379 | AR63: 379 | AT63: 399 | AU63: 399 | AV63: 696 | AW63: 432 | AX63: 520 | AY63: 0 | AZ63: Abril | BA63: 45063 | BB63: 45044
A64: Ivan Madeiras Ltda | B64: 7005303734 | C64: 3013351386 | AN64: 4189 | AO64: 4500 | AP64: 3927 | AT64: 4508 | AU64: 4141 | AV64: 3302 | AX64: 3774 | AY64: 3279 | AZ64: Abril | BA64: 45057 | BB64: 45044
A65: Waldermar Pereira Costa | B65: 7003238012 | C65: 3005520597 | AP65: 153 | AQ65: 177 | AR65: 198 | AT65: 222 | AU65: 185 | AV65: 224 | AX65: 294 | AY65: 384 | AZ65: Abril | BA65: 45073 | BB65: 45044
A66: Rita Eugênia Arthuso Melo Pacheco | B66: 7002403983 | C66: 3003167054 | AP66: 207 | AQ66: 232 | AR66: 280 | AT66: 287 | AU66: 270 | AV66: 299 | AX66: 194 | AY66: 322
A67: Ruth Maria Arthuso Melo | B67: 7200666377 | C67: 3011186347 | AP67: 202 | AQ67: 252 | AR67: 225 | AT67: 358 | AU67: 367 | AV67: 355 | AX67: 253 | AY67: 158
A68: Reginaldo Guedes | B68: 7005509346 | C68: 3006683003 | AP68: 379 | AQ68: 193 | AR68: 282 | AU68: 327 | AV68: 68 | AX68: 172 | AY68: 717 | AZ68: Abril | BA68: 45073 | BB68: 45044
A69: Academia Planeta Corpo | B69: 7200634170 | C69: 3014589151 | AU69: 17360 | AV69: 16400 | AW69: 18800 | AX69: 17627 | AY69: 2675 | AZ69: Abril | BA69: 45063 | BB69: 45044
A70: Sidney (Aplik) - Casa | B70: 7004577898 | C70: 3001450202 | AT70: 528 | AU70: 400 | AV70: 294 | AX70: 420 | AY70: 771 | AZ70: Abril | BA70: 45051 | BB70: 45036
A71: Sidney (Aplik) - Rocinha | B71: 7003340106 | C71: 3004286709 | AT71: 310 | AU71: 451 | AV71: 310 | AX71: 399 | AY71: 583 | AZ71: Abril | BA71: 45051 | BB71: 45036
A72: Sidney (Aplik) - Imobiliária | B72: 7005236808 | C72: 3007666234 | AT72: 740 | AU72: 640 | AV72: 1201 | AX72: 1234 | AY72: 0 | AZ72: Abril | BA72: 45051 | BB72: 45036
A73: Marcio Gomes Pacheco | C73: 3000097252 | AT73: 209 | AU73: 213 | AV73: 206 | AW73: 264 | AX73: 249 | AY73: 332 | AZ73: Abril | BA73: 45038 | BB73: 45027
A74: Luís Carlos Pereira | C74: 3000099014 | AR74: 203 | AS74: 261 | AT74: 435 | AU74: 342 | AV74: 258 | AW74: 228 | AX74: 244 | AY74: 567 | AZ74: Abril | BA74: 45038 | BB74: 45027
A75: Alexandre Rodrigues Sirimarco | C75: 3010964524 | AP75: 42 | AQ75: 104 | AR75: 111 | AT75: 116 | AU75: 72 | AV75: 32 | AW75: 40 | AX75: 65 | AY75: 200 | AZ75: Abril | BA75: 45063 | BB75: 45044
A76: Alexandre Rodrigues Sirimarco | C76: 3002504727 | AP76: 120 | AQ76: 137 | AR76: 145 | AT76: 138 | AU76: 83 | AV76: 111 | AW76: 157 | AX76: 128 | AY76: 105 | AZ76: Abril | BA76: 45063 | BB76: 45044
A77: Alexandre Rodrigues Sirimarco | C77: 3005361089 | AR77: 88 | AS77: 261 | AT77: 220 | AU77: 149 | AV77: 75 | AW77: 127 | AX77: 166 | AY77: 241 | AZ77: Abril | BA77: 45063 | BB77: 45044
A78: Andre Lanna de Lima e Silva | C78: 3012123920 | AR78: 305 | AU78: 541 | AV78: 265 | AW78: 387 | AX78: 336 | AY78: 610 | AZ78: Abril | BA78: 45068 | BB78: 45044
A79: C. F. Pereira da Silva Serviços | C79: 3003701876 | AP79: 620 | AQ79: 888 | AR79: 953 | AT79: 921 | AU79: 1364 | AV79: 1598 | AW79: 1966 | AX79: 1783 | AY79: 0 | AZ79: Abril | BA79: 45063 | BB79: 45044
A80: Alexander Fernandes Gonçalves | C80: 3014448834 | AQ80: 211 | AR80: 190 | AS80: 176 | AT80: 178 | AU80: 214 | AV80: 166 | AX80: 190 | AY80: 56
A81: Leonardo Jacques Gonçalves Calazans | C81: 3011850238 | AQ81: 218 | AR81: 178 | AS81: 171 | AT81: 216 | AU81: 189 | AV81: 193 | AW81: 213 | AX81: 189 | AY81: 280 | AZ81: Abril | BA81: 45052 | BB81: 45036
A82: Condomínio Edifício Atlanta Residence | C82: 3010477511 | AR82: 1097 | AS82: 1055 | AT82: 1122 | AU82: 865 | AV82: 835 | AW82: 932 | AX82: 882 | AY82: 809 | AZ82: Abril | BA82: 45057 | BB82: 45036
A83: A. F. Sampaio | C83: 3011681338 | AP83: 5200 | AQ83: 11520 | AR83: 11360 | AU83: 10960 | AV83: 15320 | AW83: 10960 | AX83: 12387 | AY83: 6780 | AZ83: Abril | BA83: 45094 | BB83: 45074
A84: A. F. Sampaio | C84: 3004244761 | AP84: 882 | AQ84: 882 | AU84: 1052 | AV84: 1071 | AW84: 1025 | AX84: 1060 | AY84: 1348 | AZ84: Abril | BA84: 45094 | BB84: 45074
A85: Alex Ferreira Sampaio | C85: 3006732798 | AQ85: 651 | AR85: 785 | AS85: 1168 | AU85: 922 | AV85: 982 | AW85: 2450 | AX85: 1705 | AY85: 753 | AZ85: Abril | BA85: 45063 | BB85: 45044
A86: Fio D Ouro Tricot & CIA Ltda | C86: 3013175523 | AQ86: 5858 | AR86: 5820 | AS86: 4441 | AU86: 1499 | AV86: 4186 | AW86: 5338 | AX86: 4005 | AY86: 19960 | AZ86: Abril | BA86: 45052 | BB86: 45036
A87: Andrezza Lorrayne Souza Vaz | C87: 3000098875 | AR87: 120 | AS87: 137 | AT87: 134 | AU87: 134 | AV87: 125 | AW87: 135 | AX87: 153 | AY87: 33 | AZ87: Abril | BA87: 45052 | BB87: 45027
A88: Roberto Dias Monteiro | C88: 3007515476 | AT88: 322 | AU88: 506 | AV88: 502 | AW88: 621 | AX88: 555 | AY88: 0 | AZ88: Abril | BA88: 45063 | BB88: 45044
A89: Ademar de Vasconcelos Pires | B89: 7009914031 | C89: 3007698929 | AO89: 229 | AP89: 237 | AQ89: 273 | AU89: 172 | AV89: 158 | AW89: 160 | AX89: 158 | AY89: 260 | AZ89: Abril | BA89: 45068 | BB89: 45044
A90: Comercial Pinho e Vasconcelos | B90: 7009992625 | C90: 3007206715 | AP90: 1284 | AQ90: 1515 | AR90: 1438 | AU90: 1472 | AV90: 1422 | AW90: 1540 | AX90: 1437 | AY90: 4401 | AZ90: Abril | BA90: 45043 | BB90: 45027
A91: Thamara Luciana Carvalho Duarte | C91: 3005379331 | AR91: 188 | AS91: 205 | AT91: 202 | AU91: 197 | AV91: 209 | AW91: 268 | AX91: 242 | AY91: 29 | AZ91: Abril | BA91: 45047 | BB91: 45027
A92: Eliane Martins Moura | C92: 3000271296 | AR92: 158 | AS92: 306 | AT92: 220 | AU92: 261 | AV92: 235 | AW92: 398 | AX92: 335 | AY92: 0 | AZ92: Abril | BA92: 45038 | BB92: 45027
A93: Ronaldo Lott Pires | C93: 3010469819 | AU93: 2830 | AV93: 2399 | AX93: 2489 | AY93: 3308
A94: Ednalva Freitas Santos | C94: 3011701509 | AQ94: 14 | AR94: 135 | AS94: 193 | AT94: 190 | AU94: 196 | AV94: 186 | AW94: 268 | AX94: 219 | AY94: 0
A95: Rafael Martins de Faria | C95: 3004263106 | AR95: 237 | AS95: 238 | AT95: 259 | AU95: 274 | AV95: 236 | AW95: 253 | AX95: 243 | AY95: 20 | AZ95: Abril | BA95: 45047 | BB95: 45027
A96: Adega Ouro Preto LTDA | B96: 7005265331 | C96: 3001088468 | AL96: 656 | AM96: 723 | AN96: 679 | AT96: 700 | AU96: 700 | AV96: 867 | AW96: 1054 | AX96: 947 | AY96: 0 | AZ96: Abril | BA96: 45057 | BB96: 45036
A97: Margarida Rocha Vianna de Oliveira (Adega) | B97: 7003220533 | C97: 3001088467 | AP97: 596 | AQ97: 554 | AR97: 572 | AV97: 518 | AW97: 682 | AX97: 606 | AY97: 54 | AZ97: Abril | BA97: 45057 | BB97: 45036
A98: Silvio Luiz Rocha Viana de Oliveira (Adega) | B98: 7005772487 | C98: 3002872985 | AP98: 182 | AQ98: 173 | AR98: 102 | AV98: 148 | AW98: 161 | AX98: 146 | AY98: 15 | AZ98: Março | BA98: 45057 | BB98: 45036
A99: Guilherme Pereira Batista | B99: 7205469797 | C99: 3013708265 | AR99: 156 | AS99: 142 | AT99: 179 | AU99: 179 | AV99: 90 | AX99: 166 | AY99: 29 | AZ99: março | BA99: 45057 | BB99: 45036
A100: Rozangela Carmelia da Conceição | C100: 3010727330 | AR100: 164 | AS100: 161 | AT100: 160 | AU100: 160 | AV100: 61 | AW100: 168 | AX100: 125 | AY100: 71 | AZ100: Abril | BA100: 45038 | BB100: 45027
...

Sheet Rateio
A1: UC | B1: Consumo Médio Ponderado | C1: Energia Injetada | D1: % Atendido | E1: Saldo GD | F1: FVS | G1: Funcesi | H1: CGH do Padre | I1: Alttos | J1: Albuquerque | K1: Fênix BL 1 | L1: Fênix BL 3 | M1: Fênix BL 7
A2: 3013533951 | C2: 42273 | E2: 0 | F2: 0 | G2: 0 | H2: 0.09 | I2: 0 | J2: 0 | L2: 0 | M2: 0
A3: 3014589151 | B3: 17627 | C3: 15035 | D3: 0.85 | E3: 2675 | F3: 0.0001 | G3: 0 | H3: 0.032 | I3: 0 | J3: 0 | K3: 0 | L3: 0 | M3: 0
A4: 3010494037 | B4: 13467 | C4: 11278 | D4: 0.84 | E4: 8076 | F4: 0.0001 | G4: 0 | H4: 0.024 | I4: 0 | J4: 0 | K4: 0 | L4: 0 | M4: 0
A5: 3009003168 | B5: 10578 | C5: 10338 | D5: 0.98 | E5: 1399 | F5: 0.0001 | G5: 0 | H5: 0.022 | I5: 0 | J5: 0 | L5: 0 | M5: 0
A6: 3011681338 | B6: 12387 | C6: 9399 | D6: 0.76 | E6: 6780 | F6: 0.0001 | G6: 0 | H6: 0.02 | I6: 0 | J6: 0 | K6: 0.15 | L6: 0.15 | M6: 0.15
A7: 3001084033 | B7: 7707 | C7: 15221 | D7: 1.98 | E7: 19766 | F7: 0.1 | G7: 0.1 | H7: 0.015 | I7: 0 | J7: 0 | K7: 0 | L7: 0 | M7: 0
A8: 3002725236 | B8: 7720 | C8: 6581 | D8: 0.85 | E8: 0 | F8: 0.0001 | G8: 0 | H8: 0.014 | I8: 0 | J8: 0 | K8: 0 | L8: 0 | M8: 0
A9: 3003870642 | B9: 6441 | C9: 5406 | D9: 0.84 | E9: 0 | F9: 0.0001 | G9: 0 | H9: 0.0115 | I9: 0 | J9: 0 | L9: 0 | M9: 0
A10: 3014085351 | B10: 5400 | C10: 5406 | D10: 1 | E10: 0 | F10: 0.0001 | G10: 0 | H10: 0.0115 | I10: 0 | J10: 0 | L10: 0 | M10: 0
A11: 3013175523 | B11: 4005 | C11: 6942 | D11: 1.73 | E11: 19960 | F11: 0.0369 | G11: 0 | H11: 0.011 | I11: 0 | J11: 0 | K11: 0.15 | L11: 0.15 | M11: 0.15
A12: 3010212220 | B12: 6824 | C12: 4702 | D12: 0.69 | E12: 0 | F12: 0.0001 | G12: 0 | H12: 0.01 | I12: 0 | J12: 0 | L12: 0 | M12: 0
A13: 3011905434 | B13: 4830 | C13: 4702 | D13: 0.97 | E13: 503 | F13: 0.0001 | G13: 0 | H13: 0.01 | I13: 0 | J13: 0 | L13: 0 | M13: 0
A14: 3003388708 | B14: 5293 | C14: 4467 | D14: 0.84 | E14: 2658 | F14: 0.0001 | G14: 0 | H14: 0.0095 | I14: 0 | J14: 0 | K14: 0 | L14: 0 | M14: 0
A15: 3000227098 | B15: 4561 | C15: 3762 | D15: 0.82 | E15: 9716 | F15: 0.0001 | G15: 0 | H15: 0.008 | I15: 0 | J15: 0 | K15: 0.15 | L15: 0.15 | M15: 0.15
A16: 3002176022 | B16: 6475 | C16: 3762 | D16: 0.58 | E16: 8587 | F16: 0.0001 | G16: 0 | H16: 0.008 | I16: 0 | J16: 0 | K16: 0 | L16: 0 | M16: 0
A17: 3006700739 | B17: 4243 | C17: 3528 | D17: 0.83 | E17: 2163 | F17: 0.0001 | G17: 0 | H17: 0.0075 | I17: 0 | J17: 0 | K17: 0 | L17: 0 | M17: 0
A18: 3004256972 | B18: 9946 | C18: 3293 | D18: 0.33 | E18: 3275 | F18: 0.0001 | G18: 0 | H18: 0.007 | I18: 0 | J18: 0 | K18: 0 | L18: 0 | M18: 0
A19: 3003562994 | B19: 3344 | C19: 3058 | D19: 0.91 | E19: 4862 | F19: 0.0001 | G19: 0 | H19: 0.0065 | I19: 0 | J19: 0 | K19: 0 | L19: 0 | M19: 0
A20: 3005437596 | B20: 1853 | C20: 2353 | D20: 1.27 | E20: 2510 | F20: 0.0001 | G20: 0 | H20: 0.005 | I20: 0 | J20: 0 | L20: 0 | M20: 0
A21: 3000184598 | B21: 2861 | C21: 2118 | D21: 0.74 | E21: 1996 | F21: 0.0001 | G21: 0 | H21: 0.0045 | I21: 0 | J21: 0 | K21: 0.1 | L21: 0.1 | M21: 0.1
A22: 3001450247 | B22: 2996 | C22: 1884 | D22: 0.63 | E22: 604 | F22: 0.0001 | G22: 0 | H22: 0.004 | I22: 0 | J22: 0 | K22: 0 | L22: 0 | M22: 0
A23: 3002906805 | B23: 2707 | C23: 1884 | D23: 0.7 | E23: 3932 | F23: 0.0001 | G23: 0 | H23: 0.004 | I23: 0 | J23: 0 | K23: 0 | L23: 0 | M23: 0
A24: 3002906806 | B24: 2262 | C24: 4777 | D24: 2.11 | E24: 4764 | F24: 0.0001 | G24: 0.1 | H24: 0.003 | I24: 0 | J24: 0 | K24: 0 | L24: 0 | M24: 0
A25: 3007206715 | B25: 1437 | C25: 2377 | D25: 1.65 | E25: 4401 | F25: 0.025 | G25: 0 | H25: 0.0025 | I25: 0 | J25: 0 | K25: 0 | L25: 0 | M25: 0
A26: 3003413089 | B26: 4533 | C26: 944 | D26: 0.21 | E26: 11041 | F26: 0.0001 | G26: 0 | H26: 0.002 | I26: 0 | J26: 0 | K26: 0.3 | L26: 0.3 | M26: 0.3
A27: 3004244761 | B27: 1060 | C27: 944 | D27: 0.89 | E27: 1348 | F27: 0.0001 | G27: 0 | H27: 0.002 | I27: 0 | J27: 0 | K27: 0 | L27: 0 | M27: 0
A28: 3000097252 | B28: 249 | C28: 48 | D28: 0.19 | E28: 332 | F28: 0.001 | G28: 0 | H28: 0 | I28: 0 | J28: 0 | K28: 0.05 | L28: 0.05 | M28: 0.05
A29: 3000098654 | B29: 206 | C29: 120 | D29: 0.59 | E29: 0 | F29: 0.0025 | G29: 0 | H29: 0 | I29: 0 | J29: 0 | L29: 0 | M29: 0
A30: 3000098875 | B30: 153 | C30: 120 | D30: 0.79 | E30: 33 | F30: 0.0025 | G30: 0 | H30: 0 | I30: 0 | J30: 0 | K30: 0 | L30: 0 | M30: 0
A31: 3000099014 | B31: 244 | C31: 144 | D31: 0.59 | E31: 567 | F31: 0.003 | G31: 0 | H31: 0 | I31: 0 | J31: 0 | K31: 0.05 | L31: 0.05 | M31: 0.05
A32: 3000236451 | B32: 319 | C32: 168 | D32: 0.53 | E32: 0 | F32: 0.0035 | G32: 0 | H32: 0 | I32: 0 | J32: 0 | L32: 0 | M32: 0
A33: 3000271296 | B33: 335 | C33: 192 | D33: 0.57 | E33: 0 | F33: 0.004 | G33: 0 | H33: 0 | I33: 0 | J33: 0 | K33: 0 | L33: 0 | M33: 0
A34: 3000271622 | B34: 255 | C34: 217 | D34: 0.85 | E34: 19 | F34: 0.0045 | G34: 0 | H34: 0 | I34: 0 | J34: 0 | K34: 0 | L34: 0 | M34: 0
A35: 3000553251 | B35: 382 | C35: 289 | D35: 0.76 | E35: 0 | F35: 0.006 | G35: 0 | H35: 0 | I35: 0 | J35: 0 | L35: 0 | M35: 0
A36: 3000881551 | B36: 1514 | C36: 962 | D36: 0.64 | E36: 0 | F36: 0.02 | G36: 0 | H36: 0 | I36: 0 | J36: 0 | K36: 0 | L36: 0 | M36: 0
A37: 3000886634 | B37: 2638 | C37: 2069 | D37: 0.78 | E37: 0 | F37: 0.043 | G37: 0 | H37: 0 | I37: 0 | J37: 0 | K37: 0 | L37: 0 | M37: 0
A38: 3000914060 | B38: 434 | C38: 48 | D38: 0.11 | E38: 0 | F38: 0.001 | G38: 0 | H38: 0 | I38: 0 | J38: 0 | K38: 0 | L38: 0 | M38: 0
A39: 3000914420 | B39: 181 | C39: 337 | D39: 1.86 | E39: 1310 | F39: 0.007 | G39: 0 | H39: 0 | I39: 0 | J39: 0 | K39: 0 | L39: 0 | M39: 0
A40: 3001088467 | B40: 606 | C40: 481 | D40: 0.79 | E40: 54 | F40: 0.01 | G40: 0 | H40: 0 | I40: 0 | J40: 0 | L40: 0 | M40: 0
A41: 3001088468 | B41: 947 | C41: 626 | D41: 0.66 | E41: 0 | F41: 0.013 | G41: 0 | H41: 0 | I41: 0 | J41: 0 | L41: 0 | M41: 0
A42: 3001268572 | B42: 3097 | C42: 5047 | D42: 1.63 | E42: 0 | F42: 0.035 | G42: 0.1 | H42: 0 | I42: 0 | J42: 0 | K42: 0 | L42: 0 | M42: 0
A43: 3001346174 | B43: 298 | C43: 289 | D43: 0.97 | E43: 159 | F43: 0.006 | G43: 0 | H43: 0 | I43: 0 | J43: 0 | K43: 0 | L43: 0 | M43: 0
A44: 3001348433 | B44: 1068 | C44: 674 | D44: 0.63 | E44: 0 | F44: 0.014 | G44: 0 | H44: 0 | I44: 0 | J44: 0 | K44: 0 | L44: 0 | M44: 0
A45: 3001449459 | B45: 1440 | C45: 3368 | D45: 2.34 | E45: 0 | F45: 0.0001 | G45: 0.1 | H45: 0 | I45: 0 | J45: 0 | K45: 0 | L45: 0 | M45: 0
A46: 3001450194 | B46: 542 | C46: 1730 | D46: 3.19 | E46: 386 | F46: 0.001 | G46: 0.05 | H46: 0 | I46: 0 | J46: 0 | K46: 0 | L46: 0 | M46: 0
A47: 3001450202 | B47: 420 | C47: 5 | D47: 0.01 | E47: 771 | F47: 0.0001 | G47: 0 | H47: 0 | I47: 0.03 | J47: 0 | K47: 0 | L47: 0 | M47: 0
A48: 3001450251 | B48: 770 | C48: 2066 | D48: 2.68 | E48: 0 | F48: 0.008 | G48: 0.05 | H48: 0 | I48: 0 | J48: 0 | K48: 0 | L48: 0 | M48: 0
A49: 3001516753 | B49: 756 | C49: 529 | D49: 0.7 | E49: 0 | F49: 0.011 | G49: 0 | H49: 0 | I49: 0 | J49: 0 | L49: 0 | M49: 0
A50: 3001780367 | B50: 203 | C50: 5 | D50: 0.02 | E50: 1782 | F50: 0.0001 | G50: 0 | H50: 0 | I50: 0 | J50: 0 | K50: 0 | L50: 0 | M50: 0
A51: 3002248046 | B51: 390 | C51: 337 | D51: 0.86 | E51: 79 | F51: 0.007 | G51: 0 | H51: 0 | I51: 0 | J51: 0 | L51: 0 | M51: 0
A52: 3002421654 | B52: 1055 | C52: 722 | D52: 0.68 | E52: 2096 | F52: 0.015 | G52: 0 | H52: 0 | I52: 0 | J52: 0 | K52: 0.05 | L52: 0.05 | M52: 0.05
A53: 3002429190 | B53: 463 | C53: 385 | D53: 0.83 | E53: 145 | F53: 0.008 | G53: 0 | H53: 0 | I53: 0 | J53: 0 | K53: 0 | L53: 0 | M53: 0
A54: 3002504727 | B54: 128 | C54: 96 | D54: 0.75 | E54: 105 | F54: 0.002 | G54: 0 | H54: 0 | I54: 0 | J54: 0 | K54: 0 | L54: 0 | M54: 0
A55: 3002619862 | B55: 882 | C55: 192 | D55: 0.22 | E55: 0 | F55: 0.004 | G55: 0 | H55: 0 | I55: 0 | J55: 0 | K55: 0 | L55: 0 | M55: 0
A56: 3002872985 | B56: 146 | C56: 96 | D56: 0.66 | E56: 15 | F56: 0.002 | G56: 0 | H56: 0 | I56: 0 | J56: 0 | L56: 0 | M56: 0
A57: 3002877896 | B57: 1264 | C57: 5 | D57: 0 | E57: 1593 | F57: 0.0001 | G57: 0 | H57: 0 | I57: 0.1 | J57: 0 | L57: 0 | M57: 0
A58: 3002906325 | B58: 388 | C58: 192 | D58: 0.5 | E58: 0 | F58: 0.004 | G58: 0 | H58: 0 | I58: 0 | J58: 0 | K58: 0 | L58: 0 | M58: 0
A59: 3002906629 | B59: 423 | C59: 385 | D59: 0.91 | E59: 169 | F59: 0.008 | G59: 0 | H59: 0 | I59: 0 | J59: 0 | L59: 0 | M59: 0
A60: 3003060564 | B60: 4047 | C60: 6155 | D60: 1.52 | E60: 7212 | F60: 0.0001 | G60: 0 | H60: 0 | I60: 0 | J60: 0.5 | L60: 0 | M60: 0
A61: 3003167054 | B61: 194 | C61: 5 | D61: 0.02 | E61: 322 | F61: 0.0001 | G61: 0 | H61: 0 | I61: 0.022 | J61: 0 | K61: 0 | L61: 0 | M61: 0
A62: 3003168714 | B62: 10027 | C62: 5 | D62: 0 | E62: 0 | F62: 0.0001 | G62: 0 | H62: 0 | I62: 0 | J62: 0 | K62: 0 | L62: 0 | M62: 0
A63: 3003171964 | B63: 173 | C63: 144 | D63: 0.83 | E63: 106 | F63: 0.003 | G63: 0 | H63: 0 | I63: 0 | J63: 0 | K63: 0 | L63: 0 | M63: 0
A64: 3003198807 | B64: 1428 | C64: 0 | D64: 0 | E64: 0 | F64: 0 | G64: 0 | H64: 0 | I64: 0 | J64: 0 | K64: 0 | L64: 0 | M64: 0
A65: 3003245697 | B65: 1614 | C65: 1107 | D65: 0.69 | E65: 10 | F65: 0.023 | G65: 0 | H65: 0 | I65: 0 | J65: 0 | K65: 0 | L65: 0 | M65: 0
A66: 3003401215 | B66: 260 | C66: 192 | D66: 0.74 | E66: 44 | F66: 0.004 | G66: 0 | H66: 0 | I66: 0 | J66: 0 | L66: 0 | M66: 0
A67: 3003586967 | B67: 289 | C67: 144 | D67: 0.5 | E67: 151 | F67: 0.003 | G67: 0 | H67: 0 | I67: 0 | J67: 0 | K67: 0 | L67: 0 | M67: 0
A68: 3003701876 | B68: 1783 | C68: 1107 | D68: 0.62 | E68: 0 | F68: 0.023 | G68: 0 | H68: 0 | I68: 0 | J68: 0 | K68: 0 | L68: 0 | M68: 0
A69: 3003858507 | B69: 3308 | C69: 1686 | D69: 0.51 | E69: 0 | F69: 0.0001 | G69: 0.05 | H69: 0 | I69: 0 | J69: 0 | K69: 0 | L69: 0 | M69: 0
A70: 3003930453 | B70: 520 | C70: 337 | D70: 0.65 | E70: 0 | F70: 0.007 | G70: 0 | H70: 0 | I70: 0 | J70: 0 | K70: 0 | L70: 0 | M70: 0
A71: 3004256543 | B71: 181 | C71: 144 | D71: 0.8 | E71: 45 | F71: 0.003 | G71: 0 | H71: 0 | I71: 0 | J71: 0 | L71: 0 | M71: 0
A72: 3004263106 | B72: 243 | C72: 192 | D72: 0.79 | E72: 20 | F72: 0.004 | G72: 0 | H72: 0 | I72: 0 | J72: 0 | K72: 0 | L72: 0 | M72: 0
A73: 3004286709 | B73: 399 | C73: 5 | D73: 0.01 | E73: 583 | F73: 0.0001 | G73: 0 | H73: 0 | I73: 0.03 | J73: 0 | K73: 0 | L73: 0 | M73: 0
A74: 3004321665 | B74: 356 | C74: 385 | D74: 1.08 | E74: 209 | F74: 0.008 | G74: 0 | H74: 0 | I74: 0 | J74: 0 | L74: 0 | M74: 0
A75: 3004338248 | B75: 134 | C75: 144 | D75: 1.08 | E75: 178 | F75: 0.003 | G75: 0 | H75: 0 | I75: 0 | J75: 0 | K75: 0 | L75: 0 | M75: 0
A76: 3004493730 | B76: 662 | C76: 722 | D76: 1.09 | E76: 114 | F76: 0.015 | G76: 0 | H76: 0 | I76: 0 | J76: 0 | L76: 0 | M76: 0
A77: 3004607095 | B77: 559 | C77: 5 | D77: 0.01 | E77: 113 | F77: 0.0001 | G77: 0 | H77: 0 | I77: 0 | J77: 0 | K77: 0 | L77: 0 | M77: 0
A78: 3004836151 | B78: 106 | C78: 96 | D78: 0.91 | E78: 61 | F78: 0.002 | G78: 0 | H78: 0 | I78: 0 | J78: 0 | L78: 0 | M78: 0
A79: 3005316449 | B79: 290 | C79: 289 | D79: 1 | E79: 192 | F79: 0.006 | G79: 0 | H79: 0 | I79: 0 | J79: 0 | K79: 0 | L79: 0 | M79: 0
A80: 3005361089 | B80: 166 | C80: 144 | D80: 0.87 | E80: 241 | F80: 0.003 | G80: 0 | H80: 0 | I80: 0 | J80: 0 | K80: 0 | L80: 0 | M80: 0
A81: 3005379331 | B81: 242 | C81: 192 | D81: 0.79 | E81: 29 | F81: 0.004 | G81: 0 | H81: 0 | I81: 0 | J81: 0 | K81: 0 | L81: 0 | M81: 0
A82: 3005520597 | B82: 294 | C82: 5 | D82: 0.02 | E82: 384 | F82: 0.0001 | G82: 0 | H82: 0 | I82: 0.016 | J82: 0 | K82: 0 | L82: 0 | M82: 0
A83: 3005534144 | B83: 258 | C83: 5 | D83: 0.02 | E83: 1179 | F83: 0.0001 | G83: 0 | H83: 0 | I83: 0 | J83: 0 | K83: 0 | L83: 0 | M83: 0
A84: 3005583221 | B84: 96 | C84: 0 | D84: 0 | E84: 1471 | F84: 0 | G84: 0 | H84: 0 | I84: 0 | J84: 0 | K84: 0 | L84: 0 | M84: 0
A85: 3006683003 | B85: 172 | C85: 5 | D85: 0.03 | E85: 717 | F85: 0.0001 | G85: 0 | H85: 0 | I85: 0.01 | J85: 0 | K85: 0 | L85: 0 | M85: 0
A86: 3006732798 | B86: 1705 | C86: 5 | D86: 0 | E86: 753 | F86: 0.0001 | G86: 0 | H86: 0 | I86: 0.09 | J86: 0 | K86: 0 | L86: 0 | M86: 0
A87: 3007395349 | B87: 247 | C87: 5 | D87: 0.02 | E87: 686 | F87: 0.0001 | G87: 0 | H87: 0 | I87: 0 | J87: 0 | K87: 0 | L87: 0 | M87: 0
A88: 3007515476 | B88: 555 | C88: 361 | D88: 0.65 | E88: 0 | F88: 0.0075 | G88: 0 | H88: 0 | I88: 0 | J88: 0 | K88: 0 | L88: 0 | M88: 0
A89: 3007592986 | B89: 255 | C89: 241 | D89: 0.94 | E89: 75 | F89: 0.005 | G89: 0 | H89: 0 | I89: 0 | J89: 0 | K89: 0 | L89: 0 | M89: 0
A90: 3007666234 | B90: 1234 | C90: 5 | D90: 0 | E90: 0 | F90: 0.0001 | G90: 0 | H90: 0 | I90: 0.07 | J90: 0 | K90: 0 | L90: 0 | M90: 0
... A92: 3007714435 | B92: 1558 | C92: 0 | D92: 0 | E92: 0 | F92: 0 | G92: 0 | H92: 0 | I92: 0 | J92: 0 | K92: 0 | L92: 0 | M92: 0
A93: 3007768063 | B93: 720 | E93: 0 | F93: 0 | G93: 0 | H93: 0 | I93: 0 | J93: 0 | L93: 0 | M93: 0
A94: 3009018668 | B94: 10500 | C94: 5 | D94: 0 | E94: 0 | F94: 0.0001 | G94: 0 | H94: 0 | I94: 0 | J94: 0 | K94: 0 | L94: 0 | M94: 0
A95: 3010469819 | B95: 2489 | C95: 5 | D95: 0 | E95: 3308 | F95: 0.0001 | G95: 0 | H95: 0 | I95: 0.19 | J95: 0 | K95: 0 | L95: 0 | M95: 0
A96: 3010470206 | B96: 222 | C96: 192 | D96: 0.87 | E96: 87 | F96: 0.004 | G96: 0 | H96: 0 | I96: 0 | J96: 0 | K96: 0 | L96: 0 | M96: 0
A97: 3010477511 | B97: 882 | C97: 866 | D97: 0.98 | E97: 809 | F97: 0.018 | G97: 0 | H97: 0 | I97: 0 | J97: 0 | K97: 0 | L97: 0 | M97: 0
A98: 3010642300 | B98: 445 | C98: 289 | D98: 0.65 | E98: 431 | F98: 0.006 | G98: 0 | H98: 0 | I98: 0 | J98: 0 | K98: 0 | L98: 0 | M98: 0
A99: 3010656684 | B99: 232 | C99: 144 | D99: 0.62 | E99: 0 | F99: 0.003 | G99: 0 | H99: 0 | I99: 0 | J99: 0 | L99: 0 | M99: 0
A100: 3010696239 | B100: 323 | C100: 241 | D100: 0.74 | E100: 310 | F100: 0.005 | G100: 0 | H100: 0 | I100: 0 | J100: 0 | L100: 0 | M100: 0
A101: 3010727330 | B101: 125 | C101: 144 | D101: 1.15 | E101: 71 | F101: 0.003 | G101: 0 | H101: 0 | I101: 0 | J101: 0 | L101: 0 | M101: 0
...
